Workbook
Name AGENCE_INFRA: REF!$J$2:$J$91
Name CDP_INFRA: REF!$I$2:$I$91
Name COEF_FCI: Recap_FCI!$I$19
Name DOM: Recap_FCI!$D$79
Name FAM_FCI: FAMILLE!$A$2:$A$122
Name IC_INFRA: REF!$H$2:$H$91
Name LOG_FCI: Recap_FCI!$D$77
Name LOT_1: Recap_FCI!$K$9
Name LOT_FCI: Recap_FCI!$K$9:$S$9
Name OFFRES: REF!$K$2:$K$91
Name PV_FCI: Recap_FCI!$F$13
Name RISQ_CHAR: Recap_FCI!$D$78
Name TECHNOLOGIES: REF!$L$2:$L$91
Name TXMO1: Recap_FCI!$E$43
Name TXMO2: Recap_FCI!$E$44
Name TXMO3: Recap_FCI!$E$45
Name TXMO4: Recap_FCI!$E$46
Name TXMO5: Recap_FCI!$E$47
Name TXMO6: Recap_FCI!$E$48
Name TXMO7: Recap_FCI!$E$49
Name TXMO8: Recap_FCI!$E$50

Sheet Page de garde

Sheet Recap_FCI
A2: Client : | C2: EXYTE | F2: N° d'Offre : | G2: [ N° d'offre ] | I2: Date réception AO : | L2: Client Preneur :
A3: Affaire : | C3: KHAZNA ORY01 — Base vie & chantier — Lot courants faibles | F3: Architecte : | G3: Woody SEALE | I3: Date Revue Offre : | L3: Maitrise d'Ouvrage :
A4: Site : | B4: Site : | C4: RD 57 — 77390 Fouju (77) | F4: Ingénieur Affaires: | G4: Woody SEALE | I4: Date Remise Offre : | L4: Aménageur / BET / AMOA :
A5: Adresse: | B5: Adresse: | F5: Agence : | I5: Date Soutenance : | L5: Maitrise d'Œuvre : | M5: Maitrise d'Œuvre :
A6: Techno: | B6: Techno: | C6: VDI / CFA / SSI / GTB | F6: BET : | I6: Date Décision : | L6: Entrepreneur Principal : | M6: Entrepreneur Principal :
A7: Offre : | F7: Date de MES Promise : | I7: Date Début Projet :
A9: RECAPITULATIF | I9: MO | J9: MAT | K9: VDI | L9: CFO | M9: CFA | N9: SSI | O9: CVC | P9: OC | Q9: VR1 | R9: VR2 | S9: VR3
A10: Total des Couts indirects : | F10: =SUM(F51:F79)/2 | G10: Remise achats sur couts directs : | I10: =SUMPRODUCT($F70:$F74,I70:I74)+SUMPRODUCT($F64:$F68,I64:I68)+SUMPRODUCT($F58:$F62,I58:I62)+SUMPRODUCT($F76:$F79,I76:I79)+SUMPRODUCT($F52:$F56,I52:I56) | J10: =SUMPRODUCT($F70:$F74,J70:J74)+SUMPRODUCT($F64:$F68,J64:J68)+SUMPRODUCT($F58:$F62,J58:J62)+SUMPRODUCT($F76:$F79,J76:J79)+SUMPRODUCT($F52:$F56,J52:J56) | K10: =K51+K57+K63+K69+K75 -> 0 | L10: =L51+L57+L63+L69+L75 -> 0 | M10: =M51+M57+M63+M69+M75 -> 0 | N10: =N51+N57+N63+N69+N75 -> 0 | O10: =O51+O57+O63+O69+O75 -> 0 | P10: =P51+P57+P63+P69+P75 -> 0 | Q10: 0 | R10: 0 | S10: 0
A11: Total des Couts Directs : | F11: =F31+F42 | I11: =F42 | J11: =F31 | K11: =K31+K42 -> 0 | L11: =L31+L42 -> 0 | M11: =M31+M42 -> 0 | N11: =N31+N42 -> 0 | O11: =O31+O42 -> 0 | P11: =P31+P42 -> 0 | Q11: 0 | R11: 0 | S11: 0
A12: Prix de Revient Total : | F12: =F10+F11-G11 | G12: Saisie manuelle du PV : | I12: =I10+I11 -> 0 | J12: =J10+J11 -> 0 | K12: =K10+K11 -> 0 | L12: =L10+L11 -> 0 | M12: =M10+M11 -> 0 | N12: =N10+N11 -> 0 | O12: =O10+O11 -> 0 | P12: =P10+P11 -> 0 | Q12: 0 | R12: 0 | S12: 0
A13: Prix de Vente : | F13: =IF(G13="",SUM(K13:P13),G13) | G13: =DPGF!AB116 | I13: =SUM($K$18:$P$18) | J13: =SUM($K$17:$P$17) | K13: =K17+K18 -> 0 | L13: =L17+L18 -> 0 | M13: =M17+M18 -> 0 | N13: =N17+N18 -> 0 | O13: =O17+O18 -> 0 | P13: =P17+P18 -> 0 | Q13: 0 | R13: 0 | S13: 0
A14: dont Prorata : | F14: =SUMPRODUCT($K$14:$P$14,$K$13:$P$13) | G14: =IF(PV_FCI>0,F14/PV_FCI,0) | J14: % de PRORATA : | K14: 0 | L14: 0 | M14: 0 | N14: 0 | O14: 0 | P14: 0 | Q14: =E14 | R14: =F14 | S14: =G14
A15: Marge : | F15: =F13-F12-F14 | G15: =IF($F$13<>0,$F$15/$F$13,) | J15: Marge MAT : | K15: 0.2 | L15: 0.2 | M15: 0.2 | N15: 0.15 | O15: 0.2 | P15: 0.2 | Q15: 0.3 | R15: 0.3 | S15: 0.3
J16: Marge MO : | K16: 0.2 | L16: 0.2 | M16: 0.2 | N16: 0.15 | O16: 0.2 | P16: 0.2 | Q16: 0.3 | R16: 0.3 | S16: 0.3
A17: Feuilles DPGF | E17: Coûts directs | F17: Prix de Vente | J17: Prix de Vente MAT : | K17: =(K$31+(IF($F$51<>0,K$51*$J$51/$F$51,0)+IF($F$57<>0,K$57*$J$57/$F$57,0)+IF($F$63<>0,K$63*$J$63/$F$63,0)+IF($F$69<>0,K$69*$J$69/$F$69,0)+IF($F$76<>0,K$76*$J$76/$F$76,0)+$F$77*K$77))/(1-K$15-K$14-$D$78-$D$79) -> 0 | L17: =(L$31+(IF($F$51<>0,L$51*$J$51/$F$51,0)+IF($F$57<>0,L$57*$J$57/$F$57,0)+IF($F$63<>0,L$63*$J$63/$F$63,0)+IF($F$69<>0,L$69*$J$69/$F$69,0)+IF($F$76<>0,L$76*$J$76/$F$76,0)+$F$77*L$77))/(1-L$15-L$14-$D$78-$D$79) -> 0 | M17: =(M$31+(IF($F$51<>0,M$51*$J$51/$F$51,0)+IF($F$57<>0,M$57*$J$57/$F$57,0)+IF($F$63<>0,M$63*$J$63/$F$63,0)+IF($F$69<>0,M$69*$J$69/$F$69,0)+IF($F$76<>0,M$76*$J$76/$F$76,0)+$F$77*M$77))/(1-M$15-M$14-$D$78-$D$79) -> 0 | N17: =(N$31+(IF($F$51<>0,N$51*$J$51/$F$51,0)+IF($F$57<>0,N$57*$J$57/$F$57,0)+IF($F$63<>0,N$63*$J$63/$F$63,0)+IF($F$69<>0,N$69*$J$69/$F$69,0)+IF($F$76<>0,N$76*$J$76/$F$76,0)+$F$77*N$77))/(1-N$15-N$14-$D$78-$D$79) -> 0 | O17: =(O$31+(IF($F$51<>0,O$51*$J$51/$F$51,0)+IF($F$57<>0,O$57*$J$57/$F$57,0)+IF($F$63<>0,O$63*$J$63/$F$63,0)+IF($F$69<>0,O$69*$J$69/$F$69,0)+IF($F$76<>0,O$76*$J$76/$F$76,0)+$F$77*O$77))/(1-O$15-O$14-$D$78-$D$79) -> 0 | P17: =(P$31+(IF($F$51<>0,P$51*$J$51/$F$51,0)+IF($F$57<>0,P$57*$J$57/$F$57,0)+IF($F$63<>0,P$63*$J$63/$F$63,0)+IF($F$69<>0,P$69*$J$69/$F$69,0)+IF($F$76<>0,P$76*$J$76/$F$76,0)+$F$77*P$77))/(1-P$15-P$14-$D$78-$D$79) -> 0 | Q17: =(Q$31+(IF($F$51<>0,Q$51*$J$51/$F$51,0)+IF($F$57<>0,Q$57*$J$57/$F$57,0)+IF($F$63<>0,Q$63*$J$63/$F$63,0)+IF($F$69<>0,Q$69*$J$69/$F$69,0)+IF($F$76<>0,Q$76*$J$76/$F$76,0)+$F$77*Q$77))/(1-Q$15-Q$14-$D$78-$D$79) | R17: =(R$31+(IF($F$51<>0,R$51*$J$51/$F$51,0)+IF($F$57<>0,R$57*$J$57/$F$57,0)+IF($F$63<>0,R$63*$J$63/$F$63,0)+IF($F$69<>0,R$69*$J$69/$F$69,0)+IF($F$76<>0,R$76*$J$76/$F$76,0)+$F$77*R$77))/(1-R$15-R$14-$D$78-$D$79) | S17: =(S$31+(IF($F$51<>0,S$51*$J$51/$F$51,0)+IF($F$57<>0,S$57*$J$57/$F$57,0)+IF($F$63<>0,S$63*$J$63/$F$63,0)+IF($F$69<>0,S$69*$J$69/$F$69,0)+IF($F$76<>0,S$76*$J$76/$F$76,0)+$F$77*S$77))/(1-S$15-S$14-$D$78-$D$79)
A18: DPGF | J18: Prix de Vente MO : | K18: =(K$42+IF($F$51<>0,K$51*$I$51/$F$51,0)+IF($F$57<>0,K$57*$I$57/$F$57,0)+IF($F$63<>0,K$63*$I$63/$F$63,0)+IF($F$69<>0,K$69*$I$69/$F$69,0)+IF($F$76<>0,K$76*$I$76/$F$76,0))/(1-K$16-K$14-$D$78-$D$79) -> 0 | L18: =(L$42+IF($F$51<>0,L$51*$I$51/$F$51,0)+IF($F$57<>0,L$57*$I$57/$F$57,0)+IF($F$63<>0,L$63*$I$63/$F$63,0)+IF($F$69<>0,L$69*$I$69/$F$69,0)+IF($F$76<>0,L$76*$I$76/$F$76,0))/(1-L$16-L$14-$D$78-$D$79) -> 0 | M18: =(M$42+IF($F$51<>0,M$51*$I$51/$F$51,0)+IF($F$57<>0,M$57*$I$57/$F$57,0)+IF($F$63<>0,M$63*$I$63/$F$63,0)+IF($F$69<>0,M$69*$I$69/$F$69,0)+IF($F$76<>0,M$76*$I$76/$F$76,0))/(1-M$16-M$14-$D$78-$D$79) -> 0 | N18: =(N$42+IF($F$51<>0,N$51*$I$51/$F$51,0)+IF($F$57<>0,N$57*$I$57/$F$57,0)+IF($F$63<>0,N$63*$I$63/$F$63,0)+IF($F$69<>0,N$69*$I$69/$F$69,0)+IF($F$76<>0,N$76*$I$76/$F$76,0))/(1-N$16-N$14-$D$78-$D$79) -> 0 | O18: =(O$42+IF($F$51<>0,O$51*$I$51/$F$51,0)+IF($F$57<>0,O$57*$I$57/$F$57,0)+IF($F$63<>0,O$63*$I$63/$F$63,0)+IF($F$69<>0,O$69*$I$69/$F$69,0)+IF($F$76<>0,O$76*$I$76/$F$76,0))/(1-O$16-O$14-$D$78-$D$79) -> 0 | P18: =(P$42+IF($F$51<>0,P$51*$I$51/$F$51,0)+IF($F$57<>0,P$57*$I$57/$F$57,0)+IF($F$63<>0,P$63*$I$63/$F$63,0)+IF($F$69<>0,P$69*$I$69/$F$69,0)+IF($F$76<>0,P$76*$I$76/$F$76,0))/(1-P$16-P$14-$D$78-$D$79) -> 0 | Q18: =(Q$42+IF($F$51<>0,Q$51*$I$51/$F$51,0)+IF($F$57<>0,Q$57*$I$57/$F$57,0)+IF($F$63<>0,Q$63*$I$63/$F$63,0)+IF($F$69<>0,Q$69*$I$69/$F$69,0)+IF($F$76<>0,Q$76*$I$76/$F$76,0))/(1-Q$16-Q$14-$D$78-$D$79) | R18: =(R$42+IF($F$51<>0,R$51*$I$51/$F$51,0)+IF($F$57<>0,R$57*$I$57/$F$57,0)+IF($F$63<>0,R$63*$I$63/$F$63,0)+IF($F$69<>0,R$69*$I$69/$F$69,0)+IF($F$76<>0,R$76*$I$76/$F$76,0))/(1-R$16-R$14-$D$78-$D$79) | S18: =(S$42+IF($F$51<>0,S$51*$I$51/$F$51,0)+IF($F$57<>0,S$57*$I$57/$F$57,0)+IF($F$63<>0,S$63*$I$63/$F$63,0)+IF($F$69<>0,S$69*$I$69/$F$69,0)+IF($F$76<>0,S$76*$I$76/$F$76,0))/(1-S$16-S$14-$D$78-$D$79)
J19: Coef. K MAT : | K19: =IF(K$31>0,K$17/K$31,0) -> 0 | L19: =IF(L$31>0,L$17/L$31,0) -> 0 | M19: =IF(M$31>0,M$17/M$31,0) -> 0 | N19: =IF(N$31>0,N$17/N$31,0) -> 0 | O19: =IF(O$31>0,O$17/O$31,0) -> 0 | P19: =IF(P$31>0,P$17/P$31,0) -> 0 | Q19: =K19 | R19: =IF(R$31<>0,R$17/R$31,0) | S19: =IF(S$31<>0,S$17/S$31,0)
J20: Coef. K MO : | K20: =IF(K$42>0,K$18/$42:$42,0) -> 0 | L20: =IF(L$42>0,L$18/$42:$42,0) -> 0 | M20: =IF(M$42>0,M$18/$42:$42,0) -> 0 | N20: =IF(N$42>0,N$18/$42:$42,0) -> 0 | O20: =IF(O$42>0,O$18/$42:$42,0) -> 0 | P20: =IF(P$42>0,P$18/$42:$42,0) -> 0 | Q20: =K20 | R20: =IF(R$42<>0,R$18/$42:$42,0) | S20: =IF(S$42<>0,S$18/$42:$42,0)
I21: Commentaires
O27: Arrondi (P/U) : | P27: 2
A29: Postes | D29: Qté | E29: P/U | F29: P/T | G29: Remarques | I29: Répartition des Couts par Lot
I30: %/MO | J30: %/MAT | K30: =LOT_1 | L30: =L9 | M30: =M9 | N30: =N9 | O30: =O9 | P30: =P9 | Q30: VR1 | R30: VR2 | S30: VR3
B31: Matériel | F31: =SUM($K$31:$P$31) | K31: 36169.53 | M31: 153192.77 | N31: 29103.4
B32: CFA-70 : Equipements Visiophonie, Interphonie | F32: =SUM($K32:$P32) | M32: 122353.36
B33: CFA-30 : Equipements Vidéo Surveillance | F33: =SUM($K33:$P33) | M33: 24045.64
B34: SSI-00 : Câblage SSI | F34: =SUM($K34:$P34) | N34: 18798
B35: VDI-00 : Cables 4p | F35: =SUM($K35:$P35) | K35: 16876.54
B36: VDI-20 : Fibres Optiques Cables, connecteurs et accessoires | F36: =SUM($K36:$P36) | K36: 12132.71
B37: SSI-10 : DETECTION INCENDIE | F37: =SUM($K37:$P37) | N37: 10305.4
B38: CVC-60 : GTB / GTC | F38: =SUM($K38:$P38) | M38: 4510
B39: VDI-50 : Baies, Coffrets, Fermes et accessoires | F39: =SUM($K39:$P39) | K39: 3960.28
B40: CFA-95 : Réseau informatique (Switch, média converter, routeur …) | F40: =SUM($K40:$P40) | K40: 3200
B41: Autres familles | F41: =SUM($K41:$P41) | M41: 2283.77
B42: Main d'Œuvre montage et intégration | F42: =SUM($F$43:$F$50) | G42: Code MO | I42: =IF(($F$31+$F$42)>0,$F$42/($F$31+$F$42),) | J42: =IF(($F$31+$F$42)>0,$F$31/($F$31+$F$42),) | K42: =SUMPRODUCT($E$43:$E$50,K$43:K$50) | L42: =SUMPRODUCT($E$43:$E$50,L$43:L$50) -> 0 | M42: =SUMPRODUCT($E$43:$E$50,M$43:M$50) -> 0 | N42: =SUMPRODUCT($E$43:$E$50,N$43:N$50) -> 0 | O42: =SUMPRODUCT($E$43:$E$50,O$43:O$50) -> 0 | P42: =SUMPRODUCT($E$43:$E$50,P$43:P$50) -> 0 | Q42: =SUMPRODUCT($E$43:$E$50,Q$43:Q$50) -> 0 | R42: =SUMPRODUCT($E$43:$E$50,R$43:R$50) -> 0 | S42: =SUMPRODUCT($E$43:$E$50,S$43:S$50) -> 0
B43: X | C43: Monteur Cableur | D43: =SUM(K43:P43) | E43: 40 | F43: =E43*D43 | G43: STE-018 | I43: 1 | J43: =1-I43 | K43: 819 | M43: 272 | N43: 262.6
C44: Technicien FO | D44: =SUM(K44:P44) -> 0 | E44: 48 | F44: =E44*D44 -> 0 | G44: STE-596 | I44: 1 | J44: =1-I44 -> 0
C45: Technicien CFO | D45: =SUM(K45:P45) -> 0 | E45: 48 | F45: =E45*D45 -> 0 | G45: STE-338 | I45: 1 | J45: =1-I45 -> 0
B46: X | C46: Technicien Cfa | D46: =SUM(K46:P46) | E46: 60 | F46: =E46*D46 | G46: STE-163 | I46: 1 | J46: =1-I46 -> 0 | K46: 152.5 | M46: 188.5 | N46: 90
C47: Technicien SSI | D47: =SUM(K47:P47) -> 0 | E47: 62 | F47: =E47*D47 -> 0 | G47: STE-136 | I47: 1 | J47: =1-I47 -> 0
C48: Technicien CVC | D48: =SUM(K48:P48) -> 0 | E48: 62 | F48: =E48*D48 -> 0 | G48: STE-335 | I48: 1 | J48: =1-I48 -> 0
B49: X | C49: RT Etudes | D49: =SUM(K49:P49) | E49: 75 | F49: =E49*D49 | G49: DOE_PROJ | I49: 1 | J49: =1-I49 -> 0 | K49: 24 | M49: 48 | N49: 14
C50: Technicien N1 | D50: =SUM(K50:P50) -> 0 | E50: 35 | F50: =E50*D50 -> 0 | G50: TIN1AV | I50: 1 | J50: =1-I50 -> 0
B51: Etude et Gouvernance Projet | F51: =SUM(F52:F56) | I51: =SUMPRODUCT(I52:I56,$F52:$F56) -> 0 | J51: =SUMPRODUCT(J52:J56,$F52:$F56) -> 0 | K51: =SUMPRODUCT(K52:K56,$F52:$F56) -> 0 | L51: =SUMPRODUCT(L52:L56,$F52:$F56) -> 0 | M51: =SUMPRODUCT(M52:M56,$F52:$F56) -> 0 | N51: =SUMPRODUCT(N52:N56,$F52:$F56) -> 0 | O51: =SUMPRODUCT(O52:O56,$F52:$F56) -> 0 | P51: =SUMPRODUCT(P52:P56,$F52:$F56) -> 0 | ... S51: =SUMPRODUCT(S52:S56,$F52:$F56) -> 0
B52: RT Conducteur de Travaux | E52: 75 | F52: =E52*D52 | G52: RT_CTVX | I52: =$I$42 | J52: =$J$42 | K52: =IF(($F$31+$F$42)>0,(K$31+K$42)/($F$31+$F$42),) -> 0 | L52: =IF(($F$31+$F$42)>0,(L$31+L$42)/($F$31+$F$42),) -> 0 | M52: =IF(($F$31+$F$42)>0,(M$31+M$42)/($F$31+$F$42),) -> 0 | N52: =IF(($F$31+$F$42)>0,(N$31+N$42)/($F$31+$F$42),) -> 0 | O52: =IF(($F$31+$F$42)>0,(O$31+O$42)/($F$31+$F$42),) -> 0 | P52: =IF(($F$31+$F$42)>0,(P$31+P$42)/($F$31+$F$42),) | Q52: =IF(($F$31+$F$42)>0,(Q$31+Q$42)/($F$31+$F$42),) | R52: =IF(($F$31+$F$42)>0,(R$31+R$42)/($F$31+$F$42),) | S52: =IF(($F$31+$F$42)>0,(S$31+S$42)/($F$31+$F$42),)
B53: RT Chef de Chantier | D53: 6 | E53: 55 | F53: =E53*D53 | G53: RT_CCHANT | I53: =$I$42 | J53: =$J$42 | K53: =IF(($F$31+$F$42)>0,(K$31+K$42)/($F$31+$F$42),) -> 0 | L53: =IF(($F$31+$F$42)>0,(L$31+L$42)/($F$31+$F$42),) -> 0 | M53: =IF(($F$31+$F$42)>0,(M$31+M$42)/($F$31+$F$42),) -> 0 | N53: =IF(($F$31+$F$42)>0,(N$31+N$42)/($F$31+$F$42),) -> 0 | O53: =IF(($F$31+$F$42)>0,(O$31+O$42)/($F$31+$F$42),) -> 0 | P53: =IF(($F$31+$F$42)>0,(P$31+P$42)/($F$31+$F$42),) -> 0 | Q53: =IF(($F$31+$F$42)>0,(Q$31+Q$42)/($F$31+$F$42),) -> 0 | R53: =IF(($F$31+$F$42)>0,(R$31+R$42)/($F$31+$F$42),) -> 0 | S53: =IF(($F$31+$F$42)>0,(S$31+S$42)/($F$31+$F$42),) -> 0
B54: RT Etudes | E54: 100 | F54: 0 | G54: DOE_PROJ | I54: =$I$42 | J54: =$J$42 | K54: =IF(($F$31+$F$42)>0,(K$31+K$42)/($F$31+$F$42),) -> 0 | L54: =IF(($F$31+$F$42)>0,(L$31+L$42)/($F$31+$F$42),) -> 0 | M54: =IF(($F$31+$F$42)>0,(M$31+M$42)/($F$31+$F$42),) -> 0 | N54: =IF(($F$31+$F$42)>0,(N$31+N$42)/($F$31+$F$42),) -> 0 | O54: =IF(($F$31+$F$42)>0,(O$31+O$42)/($F$31+$F$42),) -> 0 | P54: =IF(($F$31+$F$42)>0,(P$31+P$42)/($F$31+$F$42),) -> 0 | Q54: =IF(($F$31+$F$42)>0,(Q$31+Q$42)/($F$31+$F$42),) -> 0 | R54: =IF(($F$31+$F$42)>0,(R$31+R$42)/($F$31+$F$42),) -> 0 | S54: =IF(($F$31+$F$42)>0,(S$31+S$42)/($F$31+$F$42),) -> 0
B55: Chef de Projet | E55: 108 | F55: 0 | G55: CDP | I55: =$I$42 | J55: =$J$42 | K55: =IF(($F$31+$F$42)>0,(K$31+K$42)/($F$31+$F$42),) -> 0 | L55: =IF(($F$31+$F$42)>0,(L$31+L$42)/($F$31+$F$42),) -> 0 | M55: =IF(($F$31+$F$42)>0,(M$31+M$42)/($F$31+$F$42),) -> 0 | N55: =IF(($F$31+$F$42)>0,(N$31+N$42)/($F$31+$F$42),) -> 0 | O55: =IF(($F$31+$F$42)>0,(O$31+O$42)/($F$31+$F$42),) -> 0 | P55: =IF(($F$31+$F$42)>0,(P$31+P$42)/($F$31+$F$42),) -> 0 | Q55: =IF(($F$31+$F$42)>0,(Q$31+Q$42)/($F$31+$F$42),) -> 0 | R55: =IF(($F$31+$F$42)>0,(R$31+R$42)/($F$31+$F$42),) -> 0 | S55: =IF(($F$31+$F$42)>0,(S$31+S$42)/($F$31+$F$42),) -> 0
B56: Chiffrage | E56: 250 | F56: 0 | G56: DRP | I56: =$I$42 | J56: =$J$42 | K56: =IF(($F$31+$F$42)>0,(K$31+K$42)/($F$31+$F$42),) -> 0 | L56: =IF(($F$31+$F$42)>0,(L$31+L$42)/($F$31+$F$42),) -> 0 | M56: =IF(($F$31+$F$42)>0,(M$31+M$42)/($F$31+$F$42),) -> 0 | N56: =IF(($F$31+$F$42)>0,(N$31+N$42)/($F$31+$F$42),) -> 0 | O56: =IF(($F$31+$F$42)>0,(O$31+O$42)/($F$31+$F$42),) -> 0 | P56: =IF(($F$31+$F$42)>0,(P$31+P$42)/($F$31+$F$42),) -> 0 | Q56: =IF(($F$31+$F$42)>0,(Q$31+Q$42)/($F$31+$F$42),) -> 0 | R56: =IF(($F$31+$F$42)>0,(R$31+R$42)/($F$31+$F$42),) -> 0 | S56: =IF(($F$31+$F$42)>0,(S$31+S$42)/($F$31+$F$42),) -> 0
B57: Déplacement, transport | F57: =SUM(F58:F62) | I57: =SUMPRODUCT(I58:I62,$F58:$F62) -> 0 | J57: =SUMPRODUCT(J58:J62,$F58:$F62) -> 0 | K57: =SUMPRODUCT(K58:K62,$F58:$F62) -> 0 | L57: =SUMPRODUCT(L58:L62,$F58:$F62) -> 0 | M57: =SUMPRODUCT(M58:M62,$F58:$F62) -> 0 | N57: =SUMPRODUCT(N58:N62,$F58:$F62) -> 0 | O57: =SUMPRODUCT(O58:O62,$F58:$F62) -> 0 | P57: =SUMPRODUCT(P58:P62,$F58:$F62) -> 0 | ... S57: =SUMPRODUCT(S58:S62,$F58:$F62) -> 0
B58: Taxi | E58: 80 | F58: 0 | I58: =$I$42 | J58: =$J$42 | K58: =IF(($F$31+$F$42)>0,(K$31+K$42)/($F$31+$F$42),) -> 0 | L58: =IF(($F$31+$F$42)>0,(L$31+L$42)/($F$31+$F$42),) -> 0 | M58: =IF(($F$31+$F$42)>0,(M$31+M$42)/($F$31+$F$42),) -> 0 | N58: =IF(($F$31+$F$42)>0,(N$31+N$42)/($F$31+$F$42),) -> 0 | O58: =IF(($F$31+$F$42)>0,(O$31+O$42)/($F$31+$F$42),) -> 0 | P58: =IF(($F$31+$F$42)>0,(P$31+P$42)/($F$31+$F$42),) -> 0 | Q58: =IF(($F$31+$F$42)>0,(Q$31+Q$42)/($F$31+$F$42),) -> 0 | R58: =IF(($F$31+$F$42)>0,(R$31+R$42)/($F$31+$F$42),) -> 0 | S58: =IF(($F$31+$F$42)>0,(S$31+S$42)/($F$31+$F$42),) -> 0
B59: Train | E59: 200 | F59: 0 | I59: =$I$42 | J59: =$J$42 | K59: =IF(($F$31+$F$42)>0,(K$31+K$42)/($F$31+$F$42),) -> 0 | L59: =IF(($F$31+$F$42)>0,(L$31+L$42)/($F$31+$F$42),) -> 0 | M59: =IF(($F$31+$F$42)>0,(M$31+M$42)/($F$31+$F$42),) -> 0 | N59: =IF(($F$31+$F$42)>0,(N$31+N$42)/($F$31+$F$42),) -> 0 | O59: =IF(($F$31+$F$42)>0,(O$31+O$42)/($F$31+$F$42),) -> 0 | P59: =IF(($F$31+$F$42)>0,(P$31+P$42)/($F$31+$F$42),) -> 0 | Q59: =IF(($F$31+$F$42)>0,(Q$31+Q$42)/($F$31+$F$42),) -> 0 | R59: =IF(($F$31+$F$42)>0,(R$31+R$42)/($F$31+$F$42),) -> 0 | S59: =IF(($F$31+$F$42)>0,(S$31+S$42)/($F$31+$F$42),) -> 0
B60: Hébergement | D60: 0 | E60: 1500 | F60: =E60*D60 | I60: =$I$42 | J60: =$J$42 | K60: =IF(($F$31+$F$42)>0,(K$31+K$42)/($F$31+$F$42),) -> 0 | L60: =IF(($F$31+$F$42)>0,(L$31+L$42)/($F$31+$F$42),) -> 0 | M60: =IF(($F$31+$F$42)>0,(M$31+M$42)/($F$31+$F$42),) -> 0 | N60: =IF(($F$31+$F$42)>0,(N$31+N$42)/($F$31+$F$42),) -> 0 | O60: =IF(($F$31+$F$42)>0,(O$31+O$42)/($F$31+$F$42),) -> 0 | P60: =IF(($F$31+$F$42)>0,(P$31+P$42)/($F$31+$F$42),) -> 0 | Q60: =IF(($F$31+$F$42)>0,(Q$31+Q$42)/($F$31+$F$42),) -> 0 | R60: =IF(($F$31+$F$42)>0,(R$31+R$42)/($F$31+$F$42),) -> 0 | S60: =IF(($F$31+$F$42)>0,(S$31+S$42)/($F$31+$F$42),) -> 0
B61: Avion | E61: 650 | F61: 0 | I61: =$I$42 | J61: =$J$42 | K61: =IF(($F$31+$F$42)>0,(K$31+K$42)/($F$31+$F$42),) -> 0 | L61: =IF(($F$31+$F$42)>0,(L$31+L$42)/($F$31+$F$42),) -> 0 | M61: =IF(($F$31+$F$42)>0,(M$31+M$42)/($F$31+$F$42),) -> 0 | N61: =IF(($F$31+$F$42)>0,(N$31+N$42)/($F$31+$F$42),) -> 0 | O61: =IF(($F$31+$F$42)>0,(O$31+O$42)/($F$31+$F$42),) -> 0 | P61: =IF(($F$31+$F$42)>0,(P$31+P$42)/($F$31+$F$42),) -> 0 | Q61: =IF(($F$31+$F$42)>0,(Q$31+Q$42)/($F$31+$F$42),) -> 0 | R61: =IF(($F$31+$F$42)>0,(R$31+R$42)/($F$31+$F$42),) -> 0 | S61: =IF(($F$31+$F$42)>0,(S$31+S$42)/($F$31+$F$42),) -> 0
B62: Véhicules | D62: 6 | E62: 50 | F62: =E62*D62 | I62: =$I$42 | J62: =$J$42 | K62: =IF(($F$31+$F$42)>0,(K$31+K$42)/($F$31+$F$42),) -> 0 | L62: =IF(($F$31+$F$42)>0,(L$31+L$42)/($F$31+$F$42),) -> 0 | M62: =IF(($F$31+$F$42)>0,(M$31+M$42)/($F$31+$F$42),) -> 0 | N62: =IF(($F$31+$F$42)>0,(N$31+N$42)/($F$31+$F$42),) -> 0 | O62: =IF(($F$31+$F$42)>0,(O$31+O$42)/($F$31+$F$42),) -> 0 | P62: =IF(($F$31+$F$42)>0,(P$31+P$42)/($F$31+$F$42),) -> 0 | Q62: =IF(($F$31+$F$42)>0,(Q$31+Q$42)/($F$31+$F$42),) -> 0 | R62: =IF(($F$31+$F$42)>0,(R$31+R$42)/($F$31+$F$42),) -> 0 | S62: =IF(($F$31+$F$42)>0,(S$31+S$42)/($F$31+$F$42),) -> 0
B63: Base Vie | F63: =SUM(F64:F68) | I63: =SUMPRODUCT(I64:I68,$F64:$F68) -> 0 | J63: =SUMPRODUCT(J64:J68,$F64:$F68) -> 0 | K63: =SUMPRODUCT(K64:K68,$F64:$F68) -> 0 | L63: =SUMPRODUCT(L64:L68,$F64:$F68) -> 0 | M63: =SUMPRODUCT(M64:M68,$F64:$F68) -> 0 | N63: =SUMPRODUCT(N64:N68,$F64:$F68) -> 0 | O63: =SUMPRODUCT(O64:O68,$F64:$F68) -> 0 | P63: =SUMPRODUCT(P64:P68,$F64:$F68) -> 0 | ... S63: =SUMPRODUCT(S64:S68,$F64:$F68) -> 0
B64: Bungalows | E64: 100 | F64: 0 | G64: 100€ / jour | I64: =$I$42 | J64: =$J$42 | K64: =IF(($F$31+$F$42)>0,(K$31+K$42)/($F$31+$F$42),) -> 0 | L64: =IF(($F$31+$F$42)>0,(L$31+L$42)/($F$31+$F$42),) -> 0 | M64: =IF(($F$31+$F$42)>0,(M$31+M$42)/($F$31+$F$42),) -> 0 | N64: =IF(($F$31+$F$42)>0,(N$31+N$42)/($F$31+$F$42),) -> 0 | O64: =IF(($F$31+$F$42)>0,(O$31+O$42)/($F$31+$F$42),) -> 0 | P64: =IF(($F$31+$F$42)>0,(P$31+P$42)/($F$31+$F$42),) -> 0 | Q64: =IF(($F$31+$F$42)>0,(Q$31+Q$42)/($F$31+$F$42),) -> 0 | R64: =IF(($F$31+$F$42)>0,(R$31+R$42)/($F$31+$F$42),) -> 0 | S64: =IF(($F$31+$F$42)>0,(S$31+S$42)/($F$31+$F$42),) -> 0
B65: Cantine | E65: 5 | F65: 0 | G65: 5€/j et par personne | I65: =$I$42 | J65: =$J$42 | K65: =IF(($F$31+$F$42)>0,(K$31+K$42)/($F$31+$F$42),) -> 0 | L65: =IF(($F$31+$F$42)>0,(L$31+L$42)/($F$31+$F$42),) -> 0 | M65: =IF(($F$31+$F$42)>0,(M$31+M$42)/($F$31+$F$42),) -> 0 | N65: =IF(($F$31+$F$42)>0,(N$31+N$42)/($F$31+$F$42),) -> 0 | O65: =IF(($F$31+$F$42)>0,(O$31+O$42)/($F$31+$F$42),) -> 0 | P65: =IF(($F$31+$F$42)>0,(P$31+P$42)/($F$31+$F$42),) -> 0 | Q65: =IF(($F$31+$F$42)>0,(Q$31+Q$42)/($F$31+$F$42),) -> 0 | R65: =IF(($F$31+$F$42)>0,(R$31+R$42)/($F$31+$F$42),) -> 0 | S65: =IF(($F$31+$F$42)>0,(S$31+S$42)/($F$31+$F$42),) -> 0
B66: Vestaires | E66: 150 | F66: 0 | I66: =$I$42 | J66: =$J$42 | K66: =IF(($F$31+$F$42)>0,(K$31+K$42)/($F$31+$F$42),) -> 0 | L66: =IF(($F$31+$F$42)>0,(L$31+L$42)/($F$31+$F$42),) -> 0 | M66: =IF(($F$31+$F$42)>0,(M$31+M$42)/($F$31+$F$42),) -> 0 | N66: =IF(($F$31+$F$42)>0,(N$31+N$42)/($F$31+$F$42),) -> 0 | O66: =IF(($F$31+$F$42)>0,(O$31+O$42)/($F$31+$F$42),) -> 0 | P66: =IF(($F$31+$F$42)>0,(P$31+P$42)/($F$31+$F$42),) -> 0 | Q66: =IF(($F$31+$F$42)>0,(Q$31+Q$42)/($F$31+$F$42),) -> 0 | R66: =IF(($F$31+$F$42)>0,(R$31+R$42)/($F$31+$F$42),) -> 0 | S66: =IF(($F$31+$F$42)>0,(S$31+S$42)/($F$31+$F$42),) -> 0
B67: Sanitaire | F67: 0 | I67: =$I$42 | J67: =$J$42 | K67: =IF(($F$31+$F$42)>0,(K$31+K$42)/($F$31+$F$42),) -> 0 | L67: =IF(($F$31+$F$42)>0,(L$31+L$42)/($F$31+$F$42),) -> 0 | M67: =IF(($F$31+$F$42)>0,(M$31+M$42)/($F$31+$F$42),) -> 0 | N67: =IF(($F$31+$F$42)>0,(N$31+N$42)/($F$31+$F$42),) -> 0 | O67: =IF(($F$31+$F$42)>0,(O$31+O$42)/($F$31+$F$42),) -> 0 | P67: =IF(($F$31+$F$42)>0,(P$31+P$42)/($F$31+$F$42),) -> 0 | Q67: =IF(($F$31+$F$42)>0,(Q$31+Q$42)/($F$31+$F$42),) -> 0 | R67: =IF(($F$31+$F$42)>0,(R$31+R$42)/($F$31+$F$42),) -> 0 | S67: =IF(($F$31+$F$42)>0,(S$31+S$42)/($F$31+$F$42),) -> 0
B68: Zone Stockage, Atelier | F68: 0 | I68: =$I$42 | J68: =$J$42 | K68: =IF(($F$31+$F$42)>0,(K$31+K$42)/($F$31+$F$42),) -> 0 | L68: =IF(($F$31+$F$42)>0,(L$31+L$42)/($F$31+$F$42),) -> 0 | M68: =IF(($F$31+$F$42)>0,(M$31+M$42)/($F$31+$F$42),) -> 0 | N68: =IF(($F$31+$F$42)>0,(N$31+N$42)/($F$31+$F$42),) -> 0 | O68: =IF(($F$31+$F$42)>0,(O$31+O$42)/($F$31+$F$42),) -> 0 | P68: =IF(($F$31+$F$42)>0,(P$31+P$42)/($F$31+$F$42),) -> 0 | Q68: =IF(($F$31+$F$42)>0,(Q$31+Q$42)/($F$31+$F$42),) -> 0 | R68: =IF(($F$31+$F$42)>0,(R$31+R$42)/($F$31+$F$42),) -> 0 | S68: =IF(($F$31+$F$42)>0,(S$31+S$42)/($F$31+$F$42),) -> 0
B69: Location outillage | F69: =SUM(F70:F74) | I69: =SUMPRODUCT(I70:I74,$F70:$F74) -> 0 | J69: =SUMPRODUCT(J70:J74,$F70:$F74) -> 0 | K69: =SUMPRODUCT(K70:K74,$F70:$F74) -> 0 | L69: =SUMPRODUCT(L70:L74,$F70:$F74) -> 0 | M69: =SUMPRODUCT(M70:M74,$F70:$F74) -> 0 | N69: =SUMPRODUCT(N70:N74,$F70:$F74) -> 0 | O69: =SUMPRODUCT(O70:O74,$F70:$F74) -> 0 | P69: =SUMPRODUCT(P70:P74,$F70:$F74) -> 0 | ... S69: =SUMPRODUCT(S70:S74,$F70:$F74) -> 0
B70: Nacelle | E70: 2520 | F70: 0 | I70: =$I$42 | J70: =$J$42 | K70: =IF(($F$31+$F$42)>0,(K$31+K$42)/($F$31+$F$42),) -> 0 | L70: =IF(($F$31+$F$42)>0,(L$31+L$42)/($F$31+$F$42),) -> 0 | M70: =IF(($F$31+$F$42)>0,(M$31+M$42)/($F$31+$F$42),) -> 0 | N70: =IF(($F$31+$F$42)>0,(N$31+N$42)/($F$31+$F$42),) -> 0 | O70: =IF(($F$31+$F$42)>0,(O$31+O$42)/($F$31+$F$42),) -> 0 | P70: =IF(($F$31+$F$42)>0,(P$31+P$42)/($F$31+$F$42),) -> 0 | Q70: =IF(($F$31+$F$42)>0,(Q$31+Q$42)/($F$31+$F$42),) -> 0 | R70: =IF(($F$31+$F$42)>0,(R$31+R$42)/($F$31+$F$42),) -> 0 | S70: =IF(($F$31+$F$42)>0,(S$31+S$42)/($F$31+$F$42),) -> 0
B71: Echaffaudage | E71: 2000 | F71: 0 | I71: =$I$42 | J71: =$J$42 | K71: =IF(($F$31+$F$42)>0,(K$31+K$42)/($F$31+$F$42),) -> 0 | L71: =IF(($F$31+$F$42)>0,(L$31+L$42)/($F$31+$F$42),) -> 0 | M71: =IF(($F$31+$F$42)>0,(M$31+M$42)/($F$31+$F$42),) -> 0 | N71: =IF(($F$31+$F$42)>0,(N$31+N$42)/($F$31+$F$42),) -> 0 | O71: =IF(($F$31+$F$42)>0,(O$31+O$42)/($F$31+$F$42),) -> 0 | P71: =IF(($F$31+$F$42)>0,(P$31+P$42)/($F$31+$F$42),) -> 0 | Q71: =IF(($F$31+$F$42)>0,(Q$31+Q$42)/($F$31+$F$42),) -> 0 | R71: =IF(($F$31+$F$42)>0,(R$31+R$42)/($F$31+$F$42),) -> 0 | S71: =IF(($F$31+$F$42)>0,(S$31+S$42)/($F$31+$F$42),) -> 0
B72: Provisions (Imprimeur) | E72: 1500 | F72: 0 | I72: =$I$42 | J72: =$J$42 | K72: =IF(($F$31+$F$42)>0,(K$31+K$42)/($F$31+$F$42),) -> 0 | L72: =IF(($F$31+$F$42)>0,(L$31+L$42)/($F$31+$F$42),) -> 0 | M72: =IF(($F$31+$F$42)>0,(M$31+M$42)/($F$31+$F$42),) -> 0 | N72: =IF(($F$31+$F$42)>0,(N$31+N$42)/($F$31+$F$42),) -> 0 | O72: =IF(($F$31+$F$42)>0,(O$31+O$42)/($F$31+$F$42),) -> 0 | P72: =IF(($F$31+$F$42)>0,(P$31+P$42)/($F$31+$F$42),) -> 0 | Q72: =IF(($F$31+$F$42)>0,(Q$31+Q$42)/($F$31+$F$42),) -> 0 | R72: =IF(($F$31+$F$42)>0,(R$31+R$42)/($F$31+$F$42),) -> 0 | S72: =IF(($F$31+$F$42)>0,(S$31+S$42)/($F$31+$F$42),) -> 0
B73: GE | F73: 0 | I73: =$I$42 | J73: =$J$42 | K73: =IF(($F$31+$F$42)>0,(K$31+K$42)/($F$31+$F$42),) -> 0 | L73: =IF(($F$31+$F$42)>0,(L$31+L$42)/($F$31+$F$42),) -> 0 | M73: =IF(($F$31+$F$42)>0,(M$31+M$42)/($F$31+$F$42),) -> 0 | N73: =IF(($F$31+$F$42)>0,(N$31+N$42)/($F$31+$F$42),) -> 0 | O73: =IF(($F$31+$F$42)>0,(O$31+O$42)/($F$31+$F$42),) -> 0 | P73: =IF(($F$31+$F$42)>0,(P$31+P$42)/($F$31+$F$42),) -> 0 | Q73: =IF(($F$31+$F$42)>0,(Q$31+Q$42)/($F$31+$F$42),) -> 0 | R73: =IF(($F$31+$F$42)>0,(R$31+R$42)/($F$31+$F$42),) -> 0 | S73: =IF(($F$31+$F$42)>0,(S$31+S$42)/($F$31+$F$42),) -> 0
B74: Camion Grue | F74: 0 | I74: =$I$42 | J74: =$J$42 | K74: =IF(($F$31+$F$42)>0,(K$31+K$42)/($F$31+$F$42),) -> 0 | L74: =IF(($F$31+$F$42)>0,(L$31+L$42)/($F$31+$F$42),) -> 0 | M74: =IF(($F$31+$F$42)>0,(M$31+M$42)/($F$31+$F$42),) -> 0 | N74: =IF(($F$31+$F$42)>0,(N$31+N$42)/($F$31+$F$42),) -> 0 | O74: =IF(($F$31+$F$42)>0,(O$31+O$42)/($F$31+$F$42),) -> 0 | P74: =IF(($F$31+$F$42)>0,(P$31+P$42)/($F$31+$F$42),) -> 0 | Q74: =IF(($F$31+$F$42)>0,(Q$31+Q$42)/($F$31+$F$42),) -> 0 | R74: =IF(($F$31+$F$42)>0,(R$31+R$42)/($F$31+$F$42),) -> 0 | S74: =IF(($F$31+$F$42)>0,(S$31+S$42)/($F$31+$F$42),) -> 0
B75: Coûts divers P&L | F75: =SUM(F76:F79) | I75: =SUMPRODUCT(I76:I79,$F76:$F79) -> 0 | J75: =SUMPRODUCT(J76:J79,$F76:$F79) -> 0 | K75: =SUMPRODUCT(K76:K79,$F76:$F79) -> 0 | L75: =SUMPRODUCT(L76:L79,$F76:$F79) -> 0 | M75: =SUMPRODUCT(M76:M79,$F76:$F79) -> 0 | N75: =SUMPRODUCT(N76:N79,$F76:$F79) -> 0 | O75: =SUMPRODUCT(O76:O79,$F76:$F79) -> 0 | P75: =SUMPRODUCT(P76:P79,$F76:$F79) -> 0 | ... S75: =SUMPRODUCT(S76:S79,$F76:$F79)
B76: GARANTIE / SUPPORT | F76: =E76*D76 | G76: Sur Devis | I76: 0 | J76: =1-I76 | K76: =IF(SUM($K$31:$P$31)>0,(K$31)/SUM($K$31:$P$31),) | L76: =IF(SUM($K$31:$P$31)>0,(L$31)/SUM($K$31:$P$31),) -> 0 | M76: =IF(SUM($K$31:$P$31)>0,(M$31)/SUM($K$31:$P$31),) -> 0 | N76: =IF(SUM($K$31:$P$31)>0,(N$31)/SUM($K$31:$P$31),) -> 0 | O76: =IF(SUM($K$31:$P$31)>0,(O$31)/SUM($K$31:$P$31),) -> 0 | P76: =IF(SUM($K$31:$P$31)>0,(P$31)/SUM($K$31:$P$31),) -> 0 | Q76: =IF(SUM($K$31:$P$31)>0,(Q$31)/SUM($K$31:$P$31),) -> 0 | R76: =IF(SUM($K$31:$P$31)>0,(R$31)/SUM($K$31:$P$31),) -> 0 | S76: =IF(SUM($K$31:$P$31)>0,(S$31)/SUM($K$31:$P$31),) -> 0
B77: LOGISTIQUE | D77: 0.04 | E77: =F31 | F77: =E77*D77 | G77: % du PR | I77: 0 | J77: 1 | K77: =IF(SUM($K$31:$P$31)>0,(K$31)/SUM($K$31:$P$31),) | L77: =IF(SUM($K$31:$P$31)>0,(L$31)/SUM($K$31:$P$31),) -> 0 | M77: =IF(SUM($K$31:$P$31)>0,(M$31)/SUM($K$31:$P$31),) -> 0 | N77: =IF(SUM($K$31:$P$31)>0,(N$31)/SUM($K$31:$P$31),) -> 0 | O77: =IF(SUM($K$31:$P$31)>0,(O$31)/SUM($K$31:$P$31),) -> 0 | P77: =IF(SUM($K$31:$P$31)>0,(P$31)/SUM($K$31:$P$31),) -> 0 | Q77: =IF(SUM($K$31:$P$31)>0,(Q$31)/SUM($K$31:$P$31),) -> 0 | R77: =IF(SUM($K$31:$P$31)>0,(R$31)/SUM($K$31:$P$31),) -> 0 | S77: =IF(SUM($K$31:$P$31)>0,(S$31)/SUM($K$31:$P$31),) -> 0
B78: RISQUES ET CHARGES | D78: 0.04 | E78: =F13 | F78: =$D$78*$E$78 | G78: % du PV | I78: =$I$42 | J78: =$J$42 | K78: =IF(($F$31+$F$42)>0,(K$31+K$42)/($F$31+$F$42),) -> 0 | L78: =IF(($F$31+$F$42)>0,(L$31+L$42)/($F$31+$F$42),) -> 0 | M78: =IF(($F$31+$F$42)>0,(M$31+M$42)/($F$31+$F$42),) -> 0 | N78: =IF(($F$31+$F$42)>0,(N$31+N$42)/($F$31+$F$42),) -> 0 | O78: =IF(($F$31+$F$42)>0,(O$31+O$42)/($F$31+$F$42),) -> 0 | P78: =IF(($F$31+$F$42)>0,(P$31+P$42)/($F$31+$F$42),) -> 0 | Q78: =IF(($F$31+$F$42)>0,(Q$31+Q$42)/($F$31+$F$42),) -> 0 | R78: =IF(($F$31+$F$42)>0,(R$31+R$42)/($F$31+$F$42),) -> 0 | S78: =IF(($F$31+$F$42)>0,(S$31+S$42)/($F$31+$F$42),) -> 0
B79: DOMICILIATION | D79: 0.04 | E79: =F13 | F79: =$D$79*$E$78 | G79: % du PV | I79: =$I$42 | J79: =$J$42 | K79: =IF(($F$31+$F$42)>0,(K$31+K$42)/($F$31+$F$42),) -> 0 | L79: =IF(($F$31+$F$42)>0,(L$31+L$42)/($F$31+$F$42),) -> 0 | M79: =IF(($F$31+$F$42)>0,(M$31+M$42)/($F$31+$F$42),) -> 0 | N79: =IF(($F$31+$F$42)>0,(N$31+N$42)/($F$31+$F$42),) -> 0 | O79: =IF(($F$31+$F$42)>0,(O$31+O$42)/($F$31+$F$42),) -> 0 | P79: =IF(($F$31+$F$42)>0,(P$31+P$42)/($F$31+$F$42),) -> 0 | Q79: =IF(($F$31+$F$42)>0,(Q$31+Q$42)/($F$31+$F$42),) -> 0 | R79: =IF(($F$31+$F$42)>0,(R$31+R$42)/($F$31+$F$42),) -> 0 | S79: =IF(($F$31+$F$42)>0,(S$31+S$42)/($F$31+$F$42),) -> 0

Sheet PARA DPGF
A1: Bordereaux Client (DPGF, DQE, BOM ….) | E1: Numéro de Ligne | F1: Numéros des Colonnes | R1: Colonnes de Calcul | AA1: Colonnes de Profils de MO
A2: Création | B2: Participe au Récap | C2: Nom de la Feuille | D2: Lot par défaut | E2: Dernière ligne de Titre | F2: Constructeur | G2: Référence | H2: Description matériel | I2: Qté Achat | J2: Unité | K2: Quantité | L2: PU MAT | M2: PU MO | N2: PU MAT+MO | O2: PT MAT | P2: PT MO | Q2: PT MAT+MO | R2: LOT | S2: FAMILLE | T2: PRU MAT | U2: PRT MAT | V2: PRU MO | W2: PRT MO | X2: PRT | Y2: KMAT | Z2: KMO | AA2: Ratio MO1 | AB2: HRS MO1 Total | AC2: Ratio MO2 | AD2: HRS MO2 Total | AE2: Ratio MO3 | AF2: HRS MO3 Total | AG2: Ratio MO4 | AH2: HRS MO4 Total
A3: 43634.677 | B3: X | C3: DPGF | D3: VDI | E3: 15 | F3: =COLUMN(DPGF!$E$15) -> 5 | G3: =COLUMN(DPGF!$F$15) -> 6 | H3: =COLUMN(DPGF!$G$15) -> 7 | J3: =COLUMN(DPGF!$H$15) -> 8 | K3: =COLUMN(DPGF!$I$15) -> 9 | L3: =COLUMN(DPGF!$W$15) -> 23 | M3: =COLUMN(DPGF!$X$15) -> 24 | N3: 25 | O3: =COLUMN(DPGF!$Z$15) -> 26 | P3: =COLUMN(DPGF!$AA$15) -> 27 | Q3: 28 | R3: =COLUMN(DPGF!$C$15) -> 3 | S3: =COLUMN(DPGF!$D$15) -> 4 | T3: =COLUMN(DPGF!$J$15) -> 10 | U3: =COLUMN(DPGF!$K$15) -> 11 | V3: =COLUMN(DPGF!$R$15) -> 18 | W3: =COLUMN(DPGF!$S$15) -> 19 | X3: =COLUMN(DPGF!$T$15) -> 20 | Y3: =COLUMN(DPGF!$U$15) -> 21 | Z3: =COLUMN(DPGF!$V$15) -> 22 | AA3: =COLUMN(DPGF!$L$15) -> 12 | AB3: =COLUMN(DPGF!$M$15) -> 13 | AC3: =COLUMN(DPGF!$N$15) -> 14 | AD3: =COLUMN(DPGF!$O$15) -> 15 | AE3: =COLUMN(DPGF!$P$15) -> 16 | AF3: =COLUMN(DPGF!$Q$15) -> 17

Sheet DPGF
A5: PROSYB
A6: 3 av Jacques Chaban Delmas Roissy
A7: 77 680 Roissy en Brie
A8: France
A10: Contact : | B10: Woody SEALE
A11: Tel: | B11: 07.71.69.47.99
A12: Email: | B12: woody.seale@prosyb.com
A14: REF. | B14: DESIGNATION | C14: Equipements | H14: Unité | I14: Quantité | L14: Monteur Cableur | M14: =TXMO1 -> 40 | N14: Technicien Cfa | O14: =TXMO4 -> 60 | P14: RT Etudes | Q14: =TXMO7 -> 75 | Y14: Prix de vente
C15: LOT | D15: FAMILLE | E15: CONSTRUCTEUR | F15: REFERENCE | G15: DESCRIPTION | J15: PRU MAT | K15: PRT MAT | L15: RATIO MO | M15: HRS T | N15: RATIO MO | O15: HRS T | P15: RATIO MO | Q15: HRS T | R15: PRU MO | S15: PRT MO | T15: PR TOTAL | U15: Coef MAT | V15: Coef MO | W15: PU MAT | X15: PU MO | Y15: P.U | Z15: PT MAT | AA15: PT MO | AB15: PRIX TOTAL
B17: OBJET : KHAZNA ORY01 — Fouju (77) — Installations provisoires base vie & chantier — Lot courants faibles : informatique, audiovisuel, affichage, SSI, vidéosurveillance, GTB (DPGF lots 4 à 7)
A19: 1 | B19: INFORMATIQUE, AUDIOVISUEL & AFFICHAGES — PHASE 2 (2 MOIS) — TVA 20 %
B20: Informatique cœur de réseau
A21: 1.1 | B21: Fourniture, pose et raccordement répartiteur informatique principal dans poste énergie Hub 1, incluant switch PoE (switch d'agrégation vidéoprotection fourni par PROSYB) | C21: VDI | D21: VDI-50 | E21: OCTET PLUS / LIEN'K | F21: BAI4288CN | G21: MO : Pose baie 42U + équipement (4 h, réf. baie GTB SAFRAN) + pose switch L3 (1 h) ; paramétrage en ligne 14 | Fourniture Octet Plus devis DE044128 du 15/10/2026 (ZVK EasyLan, garantie système 25 ans ; baies LIEN'K), baie 42U 800×800 BAI4288CN (615,40 €) + bandeau 8 PC COF BAND8PC+VOY (19,45 €) = 634.85 €, ajoutés au switch L3 S57244-B0 CCF (786,03 €) → 1420.88 €. Tiroirs optiques comptés dans les lignes fibre. Pose/MO à ajouter. | H21: ens | I21: 1 | J21: 1420.88 | K21: =J21*$I21 | M21: =L21*$I21 | N21: 5 | O21: =N21*$I21 | Q21: =P21*$I21 | R21: =$L21*$M$14+$N21*$O$14+$P21*$Q$14 | S21: =R21*$I21 | T21: =$S21+$K21 | U21: =HLOOKUP($C21,Recap_FCI!$K$9:$S$20,11,FALSE) | V21: =HLOOKUP($C21,Recap_FCI!$K$9:$S$20,12,FALSE) | W21: =$J21*$U21 | X21: =$R21*$V21 | Y21: =X21+W21 | Z21: =$W21*$I21 | AA21: =$X21*$I21 | AB21: =$Y21*$I21
A22: 1.2 | B22: Fourniture, pose et raccordement répartiteur informatique principal dans poste énergie Hub 2 — switch fourni par EXYTE, pose et paramétrage PROSYB | C22: VDI | D22: VDI-50 | E22: OCTET PLUS / LIEN'K | F22: BAI4288CN | G22: MO : Pose baie 42U + équipement (4 h) + pose switch EXYTE (1 h) | Fourniture Octet Plus devis DE044128 du 15/10/2026 (ZVK EasyLan, garantie système 25 ans ; baies LIEN'K), baie 42U 800×800 BAI4288CN + bandeau 8 PC = 634.85 €. Switch informatique fourni par EXYTE (pose et paramétrage PROSYB, MO à chiffrer). | H22: ens | I22: 1 | J22: 634.85 | K22: =J22*$I22 | M22: =L22*$I22 | N22: 5 | O22: =N22*$I22 | Q22: =P22*$I22 | R22: =$L22*$M$14+$N22*$O$14+$P22*$Q$14 | S22: =R22*$I22 | T22: =$S22+$K22 | U22: =HLOOKUP($C22,Recap_FCI!$K$9:$S$20,11,FALSE) | V22: =HLOOKUP($C22,Recap_FCI!$K$9:$S$20,12,FALSE) | W22: =$J22*$U22 | X22: =$R22*$V22 | Y22: =X22+W22 | Z22: =$W22*$I22 | AA22: =$X22*$I22 | AB22: =$Y22*$I22
A23: 1.3 | B23: Fourniture, pose et raccordement répartiteur informatique secondaire Est 1 — switch fourni par EXYTE, pose et paramétrage PROSYB | C23: VDI | D23: VDI-50 | G23: MO : Intégration tiroir optique, panneau et switch EXYTE dans coffret SPIE (réf. coffret Vaires 2 h) | Coffret IP55 FOURNI ET POSÉ PAR SPIE (Ahmed, lot électricité) : retiré de l'offre et du devis Octet Plus DE044128 (COF12645MIP55 + bandeau). PROSYB installe dans ce coffret le tiroir optique et le panneau Cat. 6A (compatibilité 19"/rail DIN à valider avec SPIE). Switch informatique fourni par EXYTE (pose et paramétrage PROSYB, MO à chiffrer). | H23: ens | I23: 1 | K23: =J23*$I23 | M23: =L23*$I23 | N23: 2 | O23: =N23*$I23 | Q23: =P23*$I23 | R23: =$L23*$M$14+$N23*$O$14+$P23*$Q$14 | S23: =R23*$I23 | T23: =$S23+$K23 | U23: =HLOOKUP($C23,Recap_FCI!$K$9:$S$20,11,FALSE) | V23: =HLOOKUP($C23,Recap_FCI!$K$9:$S$20,12,FALSE) | W23: =$J23*$U23 | X23: =$R23*$V23 | Y23: =X23+W23 | Z23: =$W23*$I23 | AA23: =$X23*$I23 | AB23: =$Y23*$I23
A24: 1.4 | B24: Fourniture, pose et raccordement répartiteur informatique secondaire Est 2 — switch fourni par EXYTE, pose et paramétrage PROSYB | C24: VDI | D24: VDI-50 | G24: MO : Idem Est 1 | Coffret IP55 FOURNI ET POSÉ PAR SPIE (Ahmed, lot électricité) : retiré de l'offre et du devis Octet Plus DE044128 (COF12645MIP55 + bandeau). PROSYB installe dans ce coffret le tiroir optique et le panneau Cat. 6A (compatibilité 19"/rail DIN à valider avec SPIE). Switch informatique fourni par EXYTE (pose et paramétrage PROSYB, MO à chiffrer). | H24: ens | I24: 1 | K24: =J24*$I24 | M24: =L24*$I24 | N24: 2 | O24: =N24*$I24 | Q24: =P24*$I24 | R24: =$L24*$M$14+$N24*$O$14+$P24*$Q$14 | S24: =R24*$I24 | T24: =$S24+$K24 | U24: =HLOOKUP($C24,Recap_FCI!$K$9:$S$20,11,FALSE) | V24: =HLOOKUP($C24,Recap_FCI!$K$9:$S$20,12,FALSE) | W24: =$J24*$U24 | X24: =$R24*$V24 | Y24: =X24+W24 | Z24: =$W24*$I24 | AA24: =$X24*$I24 | AB24: =$Y24*$I24
A25: 1.5 | B25: Fourniture, pose et raccordement répartiteur informatique secondaire Est 3 — switch fourni par EXYTE, pose et paramétrage PROSYB | C25: VDI | D25: VDI-50 | G25: MO : Idem Est 1 | Coffret IP55 FOURNI ET POSÉ PAR SPIE (Ahmed, lot électricité) : retiré de l'offre et du devis Octet Plus DE044128 (COF12645MIP55 + bandeau). PROSYB installe dans ce coffret le tiroir optique et le panneau Cat. 6A (compatibilité 19"/rail DIN à valider avec SPIE). Switch informatique fourni par EXYTE (pose et paramétrage PROSYB, MO à chiffrer). | H25: ens | I25: 1 | K25: =J25*$I25 | M25: =L25*$I25 | N25: 2 | O25: =N25*$I25 | Q25: =P25*$I25 | R25: =$L25*$M$14+$N25*$O$14+$P25*$Q$14 | S25: =R25*$I25 | T25: =$S25+$K25 | U25: =HLOOKUP($C25,Recap_FCI!$K$9:$S$20,11,FALSE) | V25: =HLOOKUP($C25,Recap_FCI!$K$9:$S$20,12,FALSE) | W25: =$J25*$U25 | X25: =$R25*$V25 | Y25: =X25+W25 | Z25: =$W25*$I25 | AA25: =$X25*$I25 | AB25: =$Y25*$I25
A26: 1.6 | B26: Fourniture, pose et raccordement répartiteur informatique secondaire Ouest 1 — switch fourni par EXYTE, pose et paramétrage PROSYB | C26: VDI | D26: VDI-50 | G26: MO : Idem Est 1 | Coffret IP55 FOURNI ET POSÉ PAR SPIE (Ahmed, lot électricité) : retiré de l'offre et du devis Octet Plus DE044128 (COF12645MIP55 + bandeau). PROSYB installe dans ce coffret le tiroir optique et le panneau Cat. 6A (compatibilité 19"/rail DIN à valider avec SPIE). Switch informatique fourni par EXYTE (pose et paramétrage PROSYB, MO à chiffrer). | H26: ens | I26: 1 | K26: =J26*$I26 | M26: =L26*$I26 | N26: 2 | O26: =N26*$I26 | Q26: =P26*$I26 | R26: =$L26*$M$14+$N26*$O$14+$P26*$Q$14 | S26: =R26*$I26 | T26: =$S26+$K26 | U26: =HLOOKUP($C26,Recap_FCI!$K$9:$S$20,11,FALSE) | V26: =HLOOKUP($C26,Recap_FCI!$K$9:$S$20,12,FALSE) | W26: =$J26*$U26 | X26: =$R26*$V26 | Y26: =X26+W26 | Z26: =$W26*$I26 | AA26: =$X26*$I26 | AB26: =$Y26*$I26
A27: 1.7 | B27: Fourniture, pose et raccordement répartiteur informatique secondaire Ouest 2 — switch fourni par EXYTE, pose et paramétrage PROSYB | C27: VDI | D27: VDI-50 | G27: MO : Idem Est 1 | Coffret IP55 FOURNI ET POSÉ PAR SPIE (Ahmed, lot électricité) : retiré de l'offre et du devis Octet Plus DE044128 (COF12645MIP55 + bandeau). PROSYB installe dans ce coffret le tiroir optique et le panneau Cat. 6A (compatibilité 19"/rail DIN à valider avec SPIE). Switch informatique fourni par EXYTE (pose et paramétrage PROSYB, MO à chiffrer). | H27: ens | I27: 1 | K27: =J27*$I27 | M27: =L27*$I27 | N27: 2 | O27: =N27*$I27 | Q27: =P27*$I27 | R27: =$L27*$M$14+$N27*$O$14+$P27*$Q$14 | S27: =R27*$I27 | T27: =$S27+$K27 | U27: =HLOOKUP($C27,Recap_FCI!$K$9:$S$20,11,FALSE) | V27: =HLOOKUP($C27,Recap_FCI!$K$9:$S$20,12,FALSE) | W27: =$J27*$U27 | X27: =$R27*$V27 | Y27: =X27+W27 | Z27: =$W27*$I27 | AA27: =$X27*$I27 | AB27: =$Y27*$I27
A28: 1.8 | B28: Fourniture, pose et raccordement boucle fibre OS2 12 brins autocicatrisante depuis le répartiteur principal poste énergie Hub 1 vers répartiteurs secondaires Est 1, Est 2, Ouest 1, Ouest 2 et Ouest 3 | C28: VDI | D28: VDI-20 | E28: OCTET PLUS / ZVK | F28: ZVKLUZB12OS2 | G28: MO : Tirage fibre en fourreaux 2 900 ml à 2,5 h/100 ml (hypothèse optimiste, gros tronçons) ; fusion et tests par Octet Plus | Fourniture Octet Plus devis DE044128 du 15/10/2026 (ZVK EasyLan, garantie système 25 ans ; baies LIEN'K), boucle OS2 12 brins anti-rongeurs ZVKLUZB12OS2, 6 tronçons ≈ 2 900 ml : câble (3728.57 €) + par tronçon tiroirs LC, fusion de 24 pigtails, test photométrie Fluke Versiv2 et jarretières (561.06 € × 6) = 7094.92 €. Fusion et tests fibre réalisés par Octet Plus. | H28: ens | I28: 1 | J28: 7094.92 | K28: =J28*$I28 | L28: 72.5 | M28: =L28*$I28 | O28: =N28*$I28 | Q28: =P28*$I28 | R28: =$L28*$M$14+$N28*$O$14+$P28*$Q$14 | S28: =R28*$I28 | T28: =$S28+$K28 | U28: =HLOOKUP($C28,Recap_FCI!$K$9:$S$20,11,FALSE) | V28: =HLOOKUP($C28,Recap_FCI!$K$9:$S$20,12,FALSE) | W28: =$J28*$U28 | X28: =$R28*$V28 | Y28: =X28+W28 | Z28: =$W28*$I28 | AA28: =$X28*$I28 | AB28: =$Y28*$I28
A29: 1.9 | B29: Fourniture, pose et raccordement liaison fibre OS2 12 brins autocicatrisante depuis le répartiteur principal poste énergie Hub 1 vers le répartiteur princiapl Hub 2 | C29: VDI | D29: VDI-20 | E29: OCTET PLUS / ZVK | F29: ZVKLUZB12OS2 | G29: MO : Tirage 450 ml à 2,5 h/100 ml | Fourniture Octet Plus devis DE044128 du 15/10/2026 (ZVK EasyLan, garantie système 25 ans ; baies LIEN'K), liaison OS2 12 brins ≈ 450 ml : câble (578.57 €) + tiroirs, fusion, tests, jarretières (561.06 €) = 1139.63 €. | H29: ens | I29: 1 | J29: 1139.63 | K29: =J29*$I29 | L29: 11.25 | M29: =L29*$I29 | O29: =N29*$I29 | Q29: =P29*$I29 | R29: =$L29*$M$14+$N29*$O$14+$P29*$Q$14 | S29: =R29*$I29 | T29: =$S29+$K29 | U29: =HLOOKUP($C29,Recap_FCI!$K$9:$S$20,11,FALSE) | V29: =HLOOKUP($C29,Recap_FCI!$K$9:$S$20,12,FALSE) | W29: =$J29*$U29 | X29: =$R29*$V29 | Y29: =X29+W29 | Z29: =$W29*$I29 | AA29: =$X29*$I29 | AB29: =$Y29*$I29
A30: 1.10 | B30: Paramétrage équipements informatiques | C30: VDI | D30: DIV-70 | G30: MO : Paramétrage P2 : switch L3 3 h + Hub 2 3 h + 5 secondaires × 1,5 h (réf. Vaires) + anneau/VLAN/supervision 6 h ; BE : plan d'adressage, VLAN, synoptiques, DOE IT (16 h) | | H30: ens | I30: 1 | K30: =J30*$I30 | M30: =L30*$I30 | N30: 20 | O30: =N30*$I30 | P30: 16 | Q30: =P30*$I30 | R30: =$L30*$M$14+$N30*$O$14+$P30*$Q$14 | S30: =R30*$I30 | T30: =$S30+$K30 | U30: =HLOOKUP($C30,Recap_FCI!$K$9:$S$20,11,FALSE) | V30: =HLOOKUP($C30,Recap_FCI!$K$9:$S$20,12,FALSE) | W30: =$J30*$U30 | X30: =$R30*$V30 | Y30: =X30+W30 | Z30: =$W30*$I30 | AA30: =$X30*$I30 | AB30: =$Y30*$I30
A31: 1.11 | B31: Test de réfléctométrie | C31: VDI | D31: DIV-80 | G31: MO : Réflectométrie/photométrie réalisée par Octet Plus (incluse dans les lignes fibre) | Réflectométrie/photométrie fibre incluse dans les lignes fibre (prestation Octet Plus : raccordement et test 1310/1550 nm dans les deux sens + photométrie ISO/IEC 14763-3, dossier de mesures). | H31: ens | I31: 1 | K31: =J31*$I31 | M31: =L31*$I31 | O31: =N31*$I31 | Q31: =P31*$I31 | R31: =$L31*$M$14+$N31*$O$14+$P31*$Q$14 | S31: =R31*$I31 | T31: =$S31+$K31 | U31: =HLOOKUP($C31,Recap_FCI!$K$9:$S$20,11,FALSE) | V31: =HLOOKUP($C31,Recap_FCI!$K$9:$S$20,12,FALSE) | W31: =$J31*$U31 | X31: =$R31*$V31 | Y31: =X31+W31 | Z31: =$W31*$I31 | AA31: =$X31*$I31 | AB31: =$Y31*$I31
B32: Informatique îlots 1 et 2
A33: 1.12 | B33: Fourniture, pose et raccordement liaison cuivre répartiteur informatique principal vers équipements (postes de travail CAD + bornes WiFi), 12 prises RJ45 par îlot, soit 24 prises RJ45 au total | C33: VDI | D33: VDI-00 | E33: OCTET PLUS / ZVK | F33: ZVKCEFF1212K | G33: MO : 24 liens × 1,2 h (réf. Vaires 1,5 h/lien RJ45 30 m, optimisé en volume) | Fourniture Octet Plus devis DE044128 du 15/10/2026 (ZVK EasyLan, garantie système 25 ans ; baies LIEN'K), 24 liens Cat. 6A F/FTP 500 MHz LSFROH ZVKCEFF1212K ≈ 35 m : câble + 2 noyaux FixLink CKFAK001 + plastron 45×45 + 2 cordons Cat. 6A 1 m + quote-part platines 24 ports/passe-cordons = 770.76 €. POSE CUIVRE NON INCLUSE au devis Octet Plus (seule la fibre est raccordée) : MO PROSYB à ajouter. | H33: ens | I33: 1 | J33: 770.76 | K33: =J33*$I33 | L33: 28.8 | M33: =L33*$I33 | O33: =N33*$I33 | Q33: =P33*$I33 | R33: =$L33*$M$14+$N33*$O$14+$P33*$Q$14 | S33: =R33*$I33 | T33: =$S33+$K33 | U33: =HLOOKUP($C33,Recap_FCI!$K$9:$S$20,11,FALSE) | V33: =HLOOKUP($C33,Recap_FCI!$K$9:$S$20,12,FALSE) | W33: =$J33*$U33 | X33: =$R33*$V33 | Y33: =X33+W33 | Z33: =$W33*$I33 | AA33: =$X33*$I33 | AB33: =$Y33*$I33
A34: 1.13 | B34: Pose et raccordement borne WiFi | C34: VDI | D34: CFA-95 | G34: MO : 4 bornes × (0,75 h monteur + 0,25 h tech) (réf. Vaires 1 h + 0,5 h, optimisé) | | H34: u | I34: 4 | K34: =J34*$I34 | L34: 0.75 | M34: =L34*$I34 | N34: 0.25 | O34: =N34*$I34 | Q34: =P34*$I34 | R34: =$L34*$M$14+$N34*$O$14+$P34*$Q$14 | S34: =R34*$I34 | T34: =$S34+$K34 | U34: =HLOOKUP($C34,Recap_FCI!$K$9:$S$20,11,FALSE) | V34: =HLOOKUP($C34,Recap_FCI!$K$9:$S$20,12,FALSE) | W34: =$J34*$U34 | X34: =$R34*$V34 | Y34: =X34+W34 | Z34: =$W34*$I34 | AA34: =$X34*$I34 | AB34: =$Y34*$I34
A35: 1.14 | B35: Fourniture, pose et raccordement équipements audiovisuel salle de réunion (Un écran 85" par salle de réunion, avec enceinte caméra combinée + kit 5x micros déportés connectés) | C35: CFA | D35: CFA-70 | E35: SONEPAR | F35: 0014640130 | G35: MO : Fourniture ajoutée : 3 Rally Mic Pod supplémentaires × 252 € (estimatif, à recoter Sonepar : 4 Mic Pod/salle). MO : montage chariot + écran 86" à 2 (3 h), câblage barre/micros/lecteur/switch (2 h), essais Teams/USB (1 h) | Fourniture seule SONEPAR offre 0014640130 du 16/10/2026 (valable 31/10/2026), prix par salle : écran 86" 4K iiyama LH8665UHSB-B1 (2 188,50 €) + chariot mobile Chief Voyager LSCUW (920,00 €) + étagère Chief SCSSW (216,00 €) + barre visio Logitech Rally Bar (3 400,00 €) + micro LOG025 (252,00 €) + lecteur Navori StiX 3800 (450,00 €) + licence Navori PRD-1011571 (450,00 €) + switch PoE 8 ports TP-Link SG2210MP (164,19 €) + cordons HDMI 10 m (42,89 €) et 2 m (11,58 €) + D3E (1,49 €) + quote-part port (6,00 €) = 8 102,65 €. À RECOTER : micro coté = micro d'extension MeetUp, NON compatible Rally Bar (doc. Logitech) ; le DCE demande 5 micros, mémoire = 4 Logitech Rally Mic Pod 989-000430 (maximum Rally Bar) → demander prix Sonepar. Chariot Chief annoncé 50-85", écran 86"/49 kg (charge 79 kg OK) : compatibilité à faire valider. Variante Rally Bar Huddle (1 850 €) non retenue. Pose/câblage/paramétrage/MO à ajouter. | H35: u | I35: 3 | J35: 8858.65 | K35: =J35*$I35 | L35: 3 | M35: =L35*$I35 | N35: 3 | O35: =N35*$I35 | Q35: =P35*$I35 | R35: =$L35*$M$14+$N35*$O$14+$P35*$Q$14 | S35: =R35*$I35 | T35: =$S35+$K35 | U35: =HLOOKUP($C35,Recap_FCI!$K$9:$S$20,11,FALSE) | V35: =HLOOKUP($C35,Recap_FCI!$K$9:$S$20,12,FALSE) | W35: =$J35*$U35 | X35: =$R35*$V35 | Y35: =X35+W35 | Z35: =$W35*$I35 | AA35: =$X35*$I35 | AB35: =$Y35*$I35
A36: 1.15 | B36: Recettage cuivre | C36: VDI | D36: DIV-80 | G36: MO : Certification classe EA : 24 liens × 0,1 h + rapport 1 h (certificateur PROSYB supposé disponible) | Certification cuivre classe EA non chiffrée par Octet Plus : à réaliser par PROSYB (testeur de certification) ou à demander à Octet Plus. | H36: ens | I36: 1 | K36: =J36*$I36 | M36: =L36*$I36 | N36: 3.4 | O36: =N36*$I36 | Q36: =P36*$I36 | R36: =$L36*$M$14+$N36*$O$14+$P36*$Q$14 | S36: =R36*$I36 | T36: =$S36+$K36 | U36: =HLOOKUP($C36,Recap_FCI!$K$9:$S$20,11,FALSE) | V36: =HLOOKUP($C36,Recap_FCI!$K$9:$S$20,12,FALSE) | W36: =$J36*$U36 | X36: =$R36*$V36 | Y36: =X36+W36 | Z36: =$W36*$I36 | AA36: =$X36*$I36 | AB36: =$Y36*$I36
AB38: =SUBTOTAL(9,AB20:AB36)
A39: 2 | B39: INFORMATIQUE, AUDIOVISUEL & AFFICHAGES — PHASE 3 (5 MOIS) — TVA 20 %
B40: Informatique cœur de réseau
A41: 2.1 | B41: Sans objet | C41: VDI | D41: VDI-00 | H41: ens | I41: 1 | K41: =J41*$I41 | M41: =L41*$I41 | O41: =N41*$I41 | Q41: =P41*$I41 | R41: =$L41*$M$14+$N41*$O$14+$P41*$Q$14 | S41: =R41*$I41 | T41: =$S41+$K41 | U41: =HLOOKUP($C41,Recap_FCI!$K$9:$S$20,11,FALSE) | V41: =HLOOKUP($C41,Recap_FCI!$K$9:$S$20,12,FALSE) | W41: =$J41*$U41 | X41: =$R41*$V41 | Y41: =X41+W41 | Z41: =$W41*$I41 | AA41: =$X41*$I41 | AB41: =$Y41*$I41
B42: Informatique îlots 3 à 10
A43: 2.2 | B43: Fourniture, pose et raccordement liaisons cuivre répartiteur informatique principal vers équipements (postes de travail CAD + bornes WiFi), 12 prises RJ45 par îlot, soit 96 prises RJ45 au total | C43: VDI | D43: VDI-00 | E43: OCTET PLUS / ZVK | F43: ZVKCEFF1212K | G43: MO : 96 liens × 1,2 h | Fourniture Octet Plus devis DE044128 du 15/10/2026 (ZVK EasyLan, garantie système 25 ans ; baies LIEN'K), 96 liens Cat. 6A F/FTP ≈ 35 m, même composition que P2 = 3083.05 €. Pose cuivre non incluse : MO PROSYB à ajouter. | H43: ens | I43: 1 | J43: 3083.05 | K43: =J43*$I43 | L43: 115.2 | M43: =L43*$I43 | O43: =N43*$I43 | Q43: =P43*$I43 | R43: =$L43*$M$14+$N43*$O$14+$P43*$Q$14 | S43: =R43*$I43 | T43: =$S43+$K43 | U43: =HLOOKUP($C43,Recap_FCI!$K$9:$S$20,11,FALSE) | V43: =HLOOKUP($C43,Recap_FCI!$K$9:$S$20,12,FALSE) | W43: =$J43*$U43 | X43: =$R43*$V43 | Y43: =X43+W43 | Z43: =$W43*$I43 | AA43: =$X43*$I43 | AB43: =$Y43*$I43
A44: 2.3 | B44: Fourniture, pose et raccordement borne WiFi | C44: VDI | D44: CFA-95 | E44: UBIQUITI (estimatif) | F44: U6 Pro | G44: MO : Fourniture borne Wi-Fi 6 PoE type Ubiquiti U6 Pro 160 € (estimatif, prix budgétaire de repli) ; pose 0,75 h + 0,25 h | | H44: u | I44: 20 | J44: 160 | K44: =J44*$I44 | L44: 0.75 | M44: =L44*$I44 | N44: 0.25 | O44: =N44*$I44 | Q44: =P44*$I44 | R44: =$L44*$M$14+$N44*$O$14+$P44*$Q$14 | S44: =R44*$I44 | T44: =$S44+$K44 | U44: =HLOOKUP($C44,Recap_FCI!$K$9:$S$20,11,FALSE) | V44: =HLOOKUP($C44,Recap_FCI!$K$9:$S$20,12,FALSE) | W44: =$J44*$U44 | X44: =$R44*$V44 | Y44: =X44+W44 | Z44: =$W44*$I44 | AA44: =$X44*$I44 | AB44: =$Y44*$I44
A45: 2.4 | B45: Fourniture, pose et raccordement équipements audiovisuel salle de réunion (Un écran 85" par salle de réunion, avec enceinte caméra combinée + kit 5x micros déportés connectés) | C45: CFA | D45: CFA-70 | E45: SONEPAR | F45: 0014640130 | G45: MO : Idem P2 | Fourniture seule SONEPAR offre 0014640130 du 16/10/2026 (valable 31/10/2026), prix par salle : écran 86" 4K iiyama LH8665UHSB-B1 (2 188,50 €) + chariot mobile Chief Voyager LSCUW (920,00 €) + étagère Chief SCSSW (216,00 €) + barre visio Logitech Rally Bar (3 400,00 €) + micro LOG025 (252,00 €) + lecteur Navori StiX 3800 (450,00 €) + licence Navori PRD-1011571 (450,00 €) + switch PoE 8 ports TP-Link SG2210MP (164,19 €) + cordons HDMI 10 m (42,89 €) et 2 m (11,58 €) + D3E (1,49 €) + quote-part port (6,00 €) = 8 102,65 €. À RECOTER : micro coté = micro d'extension MeetUp, NON compatible Rally Bar (doc. Logitech) ; le DCE demande 5 micros, mémoire = 4 Logitech Rally Mic Pod 989-000430 (maximum Rally Bar) → demander prix Sonepar. Chariot Chief annoncé 50-85", écran 86"/49 kg (charge 79 kg OK) : compatibilité à faire valider. Variante Rally Bar Huddle (1 850 €) non retenue. Pose/câblage/paramétrage/MO à ajouter. | H45: u | I45: 7 | J45: 8858.65 | K45: =J45*$I45 | L45: 3 | M45: =L45*$I45 | N45: 3 | O45: =N45*$I45 | Q45: =P45*$I45 | R45: =$L45*$M$14+$N45*$O$14+$P45*$Q$14 | S45: =R45*$I45 | T45: =$S45+$K45 | U45: =HLOOKUP($C45,Recap_FCI!$K$9:$S$20,11,FALSE) | V45: =HLOOKUP($C45,Recap_FCI!$K$9:$S$20,12,FALSE) | W45: =$J45*$U45 | X45: =$R45*$V45 | Y45: =X45+W45 | Z45: =$W45*$I45 | AA45: =$X45*$I45 | AB45: =$Y45*$I45
A46: 2.5 | B46: Recettage cuivre | C46: VDI | D46: DIV-80 | G46: MO : Certification 96 liens × 0,1 h + rapport 1 h | Certification cuivre classe EA non chiffrée par Octet Plus : PROSYB ou demande complémentaire. | H46: ens | I46: 1 | K46: =J46*$I46 | M46: =L46*$I46 | N46: 10.6 | O46: =N46*$I46 | Q46: =P46*$I46 | R46: =$L46*$M$14+$N46*$O$14+$P46*$Q$14 | S46: =R46*$I46 | T46: =$S46+$K46 | U46: =HLOOKUP($C46,Recap_FCI!$K$9:$S$20,11,FALSE) | V46: =HLOOKUP($C46,Recap_FCI!$K$9:$S$20,12,FALSE) | W46: =$J46*$U46 | X46: =$R46*$V46 | Y46: =X46+W46 | Z46: =$W46*$I46 | AA46: =$X46*$I46 | AB46: =$Y46*$I46
B47: Informatique chantier
A48: 2.6 | B48: Fourniture, pose et raccordement répartiteur secondaire bâtiments annexes | C48: VDI | D48: VDI-20 | E48: OCTET PLUS / ZVK | F48: ZVKLUZB12OS2 | G48: MO : Par annexe : tirage fibre 150 ml (3,75 h) + intégration dans coffret SPIE (2 h) | Fourniture Octet Plus devis DE044128 du 15/10/2026 (ZVK EasyLan, garantie système 25 ans ; baies LIEN'K), par annexe : liaison OS2 12 brins ≈ 150 ml avec tiroir, fusion, tests = 753.92 €. Coffret IP55 fourni et posé par SPIE (retiré du devis Octet Plus). Switch fourni par EXYTE. | H48: u | I48: 2 | J48: 753.92 | K48: =J48*$I48 | L48: 3.75 | M48: =L48*$I48 | N48: 2 | O48: =N48*$I48 | Q48: =P48*$I48 | R48: =$L48*$M$14+$N48*$O$14+$P48*$Q$14 | S48: =R48*$I48 | T48: =$S48+$K48 | U48: =HLOOKUP($C48,Recap_FCI!$K$9:$S$20,11,FALSE) | V48: =HLOOKUP($C48,Recap_FCI!$K$9:$S$20,12,FALSE) | W48: =$J48*$U48 | X48: =$R48*$V48 | Y48: =X48+W48 | Z48: =$W48*$I48 | AA48: =$X48*$I48 | AB48: =$Y48*$I48
A49: 2.7 | B49: Fourniture, pose et raccordement liaisons RJ45 CAT6A F/STP bâtiments techniques & extérieurs | C49: VDI | D49: VDI-00 | E49: OCTET PLUS / ZVK | F49: ZVKCEFF1212K | G49: MO : Par liaison extérieure ≈ 60 m sous fourreau : 2,5 h (réf. ECLAIRION 2,5 h + 0,5 h pour ≤ 30 m, optimisé) ; test en ligne 32 | Fourniture Octet Plus devis DE044128 du 15/10/2026 (ZVK EasyLan, garantie système 25 ans ; baies LIEN'K), par liaison : câble Cat. 6A F/FTP ≈ 60 m + 2 noyaux + plastron + 2 cordons + quote-part platines = 48.71 €. Câble intérieur LSFROH : prévoir fourreau/protection pour les parcours extérieurs. Pose non incluse. | H49: u | I49: 30 | J49: 48.71 | K49: =J49*$I49 | L49: 2.5 | M49: =L49*$I49 | O49: =N49*$I49 | Q49: =P49*$I49 | R49: =$L49*$M$14+$N49*$O$14+$P49*$Q$14 | S49: =R49*$I49 | T49: =$S49+$K49 | U49: =HLOOKUP($C49,Recap_FCI!$K$9:$S$20,11,FALSE) | V49: =HLOOKUP($C49,Recap_FCI!$K$9:$S$20,12,FALSE) | W49: =$J49*$U49 | X49: =$R49*$V49 | Y49: =X49+W49 | Z49: =$W49*$I49 | AA49: =$X49*$I49 | AB49: =$Y49*$I49
A50: 2.8 | B50: Recettage cuivre | C50: VDI | D50: DIV-80 | G50: MO : Certification 30 liaisons × 0,15 h | Certification cuivre non chiffrée par Octet Plus. | H50: ens | I50: 1 | K50: =J50*$I50 | M50: =L50*$I50 | N50: 4.5 | O50: =N50*$I50 | Q50: =P50*$I50 | R50: =$L50*$M$14+$N50*$O$14+$P50*$Q$14 | S50: =R50*$I50 | T50: =$S50+$K50 | U50: =HLOOKUP($C50,Recap_FCI!$K$9:$S$20,11,FALSE) | V50: =HLOOKUP($C50,Recap_FCI!$K$9:$S$20,12,FALSE) | W50: =$J50*$U50 | X50: =$R50*$V50 | Y50: =X50+W50 | Z50: =$W50*$I50 | AA50: =$X50*$I50 | AB50: =$Y50*$I50
B51: Afficheurs chantier
A52: 2.9 | B52: Fourniture, pose et raccordement afficheurs chantier extérieur + Support | C52: CFA | D52: CFA-70 | E52: SONEPAR | F52: 0014640130 | G52: MO : Fourniture ajoutée : supports (3 bras muraux antivol 250 € + 3 totems ERARD ≈ 1 300 €) moyenne 775 €/u (estimatif, prix Sonepar attendu). MO : mural 4 h / totem 8 h à 2 (moy. 6 h) + raccordement et mise en service 1,5 h (réf. estimation afficheurs 10/10, optimisée) | Fourniture seule SONEPAR offre 0014640130 du 16/10/2026, prix par afficheur : écran extérieur Samsung OHDX 55" LH55OHDEBGBXEN (3 500 cd/m², IP56) (3 752,00 €) + lecteur Navori StiX 3800 (450,00 €) + licence Navori (450,00 €) + switch PoE TP-Link SG2210MP (164,19 €) + cordon HDMI 2 m (11,58 €) + D3E (0,04 €) + quote-part port (25,00 €) = 4 852,81 €. SUPPORTS NON CHIFFRÉS (prix attendu Sonepar début de semaine) : 3 totems ERARD PRO OUTDOOH réf. 665155 (prévu pour OH55F, écran en portrait — compatibilité OHDX à confirmer par ERARD) + 3 bras muraux orientables antivol. Pose/MO à ajouter. | H52: u | I52: 6 | J52: 5627.81 | K52: =J52*$I52 | L52: 6 | M52: =L52*$I52 | N52: 1.5 | O52: =N52*$I52 | Q52: =P52*$I52 | R52: =$L52*$M$14+$N52*$O$14+$P52*$Q$14 | S52: =R52*$I52 | T52: =$S52+$K52 | U52: =HLOOKUP($C52,Recap_FCI!$K$9:$S$20,11,FALSE) | V52: =HLOOKUP($C52,Recap_FCI!$K$9:$S$20,12,FALSE) | W52: =$J52*$U52 | X52: =$R52*$V52 | Y52: =X52+W52 | Z52: =$W52*$I52 | AA52: =$X52*$I52 | AB52: =$Y52*$I52
A53: 2.10 | B53: Paramétrage | C53: CFA | D53: DIV-70 | G53: MO : Serveur de diffusion Navori QL sur site 1 100 € (estimatif). Paramétrage serveur, 16 lecteurs, groupes, alerte prioritaire, programmation (16 h) ; BE : charte + 10 modèles de contenus FR/EN, formation EXYTE ½ j, DOE (12 h) | Licences Navori incluses dans la ligne afficheurs (et salles). Serveur de diffusion Navori QL sur site (baie Hub 1) NON chiffré par Sonepar : PC serveur + éventuelle licence serveur à chiffrer ; durée licence PRD-1011571 (perpétuelle sur site ou abonnement) à confirmer. Paramétrage, charte et formation = MO PROSYB à ajouter. | H53: ens | I53: 1 | J53: 1100 | K53: =J53*$I53 | M53: =L53*$I53 | N53: 16 | O53: =N53*$I53 | P53: 12 | Q53: =P53*$I53 | R53: =$L53*$M$14+$N53*$O$14+$P53*$Q$14 | S53: =R53*$I53 | T53: =$S53+$K53 | U53: =HLOOKUP($C53,Recap_FCI!$K$9:$S$20,11,FALSE) | V53: =HLOOKUP($C53,Recap_FCI!$K$9:$S$20,12,FALSE) | W53: =$J53*$U53 | X53: =$R53*$V53 | Y53: =X53+W53 | Z53: =$W53*$I53 | AA53: =$X53*$I53 | AB53: =$Y53*$I53
AB55: =SUBTOTAL(9,AB40:AB53)
A56: 3 | B56: INFORMATIQUE — PHASE 4 (17 MOIS) — TVA 20 %
B57: Informatique cœur de réseau
A58: 3.1 | B58: Fourniture, pose et raccordement répartiteur informatique principal dans poste énergie Hub 3 — switch fourni par EXYTE, pose et paramétrage PROSYB | C58: VDI | D58: VDI-50 | E58: OCTET PLUS / LIEN'K | F58: BAI4288CN | G58: MO : Pose baie 42U + switch EXYTE | Fourniture Octet Plus devis DE044128 du 15/10/2026 (ZVK EasyLan, garantie système 25 ans ; baies LIEN'K), baie 42U 800×800 + bandeau 8 PC = 634.85 €. Switch fourni par EXYTE. | H58: ens | I58: 1 | J58: 634.85 | K58: =J58*$I58 | M58: =L58*$I58 | N58: 5 | O58: =N58*$I58 | Q58: =P58*$I58 | R58: =$L58*$M$14+$N58*$O$14+$P58*$Q$14 | S58: =R58*$I58 | T58: =$S58+$K58 | U58: =HLOOKUP($C58,Recap_FCI!$K$9:$S$20,11,FALSE) | V58: =HLOOKUP($C58,Recap_FCI!$K$9:$S$20,12,FALSE) | W58: =$J58*$U58 | X58: =$R58*$V58 | Y58: =X58+W58 | Z58: =$W58*$I58 | AA58: =$X58*$I58 | AB58: =$Y58*$I58
A59: 3.2 | B59: Fourniture, pose et raccordement fibre OS2 12 brins depuis répartiteur principal poste énergie Hub 1 vers répartiteur principal poste énergie Hub 3 | C59: VDI | D59: VDI-20 | E59: OCTET PLUS / ZVK | F59: ZVKLUZB12OS2 | G59: MO : Tirage 150 ml | Fourniture Octet Plus devis DE044128 du 15/10/2026 (ZVK EasyLan, garantie système 25 ans ; baies LIEN'K), liaison OS2 12 brins ≈ 150 ml + tiroirs, fusion, tests = 753.92 €. | H59: ens | I59: 1 | J59: 753.92 | K59: =J59*$I59 | L59: 3.75 | M59: =L59*$I59 | O59: =N59*$I59 | Q59: =P59*$I59 | R59: =$L59*$M$14+$N59*$O$14+$P59*$Q$14 | S59: =R59*$I59 | T59: =$S59+$K59 | U59: =HLOOKUP($C59,Recap_FCI!$K$9:$S$20,11,FALSE) | V59: =HLOOKUP($C59,Recap_FCI!$K$9:$S$20,12,FALSE) | W59: =$J59*$U59 | X59: =$R59*$V59 | Y59: =X59+W59 | Z59: =$W59*$I59 | AA59: =$X59*$I59 | AB59: =$Y59*$I59
A60: 3.3 | B60: Fourniture, pose et raccordement fibre OS2 12 brins depuis répartiteur principal poste énergie Hub 3 vers répartiteurs secondaires A (Ilots 1 à 10) | C60: VDI | D60: VDI-20 | E60: OCTET PLUS / ZVK | F60: ZVKLUZB12OS2 | G60: MO : Tirage 200 ml | Fourniture Octet Plus devis DE044128 du 15/10/2026 (ZVK EasyLan, garantie système 25 ans ; baies LIEN'K), liaison OS2 12 brins ≈ 200 ml + tiroirs, fusion, tests = 818.20 €. | H60: ens | I60: 1 | J60: 818.2 | K60: =J60*$I60 | L60: 5 | M60: =L60*$I60 | O60: =N60*$I60 | Q60: =P60*$I60 | R60: =$L60*$M$14+$N60*$O$14+$P60*$Q$14 | S60: =R60*$I60 | T60: =$S60+$K60 | U60: =HLOOKUP($C60,Recap_FCI!$K$9:$S$20,11,FALSE) | V60: =HLOOKUP($C60,Recap_FCI!$K$9:$S$20,12,FALSE) | W60: =$J60*$U60 | X60: =$R60*$V60 | Y60: =X60+W60 | Z60: =$W60*$I60 | AA60: =$X60*$I60 | AB60: =$Y60*$I60
A61: 3.4 | B61: Fourniture, pose et raccordement fibre OS2 12 brins depuis répartiteur principal poste énergie Hub 3 vers répartiteurs secondaires B (Ilots 11 à 20) | C61: VDI | D61: VDI-20 | E61: OCTET PLUS / ZVK | F61: ZVKLUZB12OS2 | G61: MO : Tirage 200 ml | Fourniture Octet Plus devis DE044128 du 15/10/2026 (ZVK EasyLan, garantie système 25 ans ; baies LIEN'K), liaison OS2 12 brins ≈ 200 ml + tiroirs, fusion, tests = 818.20 €. | H61: ens | I61: 1 | J61: 818.2 | K61: =J61*$I61 | L61: 5 | M61: =L61*$I61 | O61: =N61*$I61 | Q61: =P61*$I61 | R61: =$L61*$M$14+$N61*$O$14+$P61*$Q$14 | S61: =R61*$I61 | T61: =$S61+$K61 | U61: =HLOOKUP($C61,Recap_FCI!$K$9:$S$20,11,FALSE) | V61: =HLOOKUP($C61,Recap_FCI!$K$9:$S$20,12,FALSE) | W61: =$J61*$U61 | X61: =$R61*$V61 | Y61: =X61+W61 | Z61: =$W61*$I61 | AA61: =$X61*$I61 | AB61: =$Y61*$I61
A62: 3.5 | B62: Paramétrage équipements informatiques | C62: VDI | D62: DIV-70 | G62: MO : Paramétrage P4 : cœur Hub 3 (3 h) + piles d'accès A/B (≈ 8 switchs × 1,5 h) + bascule ; BE : mise à jour adressage, synoptiques, DOE | | H62: ens | I62: 1 | K62: =J62*$I62 | M62: =L62*$I62 | N62: 16 | O62: =N62*$I62 | P62: 8 | Q62: =P62*$I62 | R62: =$L62*$M$14+$N62*$O$14+$P62*$Q$14 | S62: =R62*$I62 | T62: =$S62+$K62 | U62: =HLOOKUP($C62,Recap_FCI!$K$9:$S$20,11,FALSE) | V62: =HLOOKUP($C62,Recap_FCI!$K$9:$S$20,12,FALSE) | W62: =$J62*$U62 | X62: =$R62*$V62 | Y62: =X62+W62 | Z62: =$W62*$I62 | AA62: =$X62*$I62 | AB62: =$Y62*$I62
A63: 3.6 | B63: Test de réfléctométrie | C63: VDI | D63: DIV-80 | G63: MO : Tests fibre P4 par Octet Plus | Tests fibre P4 inclus dans les lignes fibre (prestation Octet Plus en 4 phases). | H63: ens | I63: 1 | K63: =J63*$I63 | M63: =L63*$I63 | O63: =N63*$I63 | Q63: =P63*$I63 | R63: =$L63*$M$14+$N63*$O$14+$P63*$Q$14 | S63: =R63*$I63 | T63: =$S63+$K63 | U63: =HLOOKUP($C63,Recap_FCI!$K$9:$S$20,11,FALSE) | V63: =HLOOKUP($C63,Recap_FCI!$K$9:$S$20,12,FALSE) | W63: =$J63*$U63 | X63: =$R63*$V63 | Y63: =X63+W63 | Z63: =$W63*$I63 | AA63: =$X63*$I63 | AB63: =$Y63*$I63
B64: Informatique îlots 1 à 20
A65: 3.7 | B65: Fourniture, pose et raccordement répartiteur informatique secondaires base vie phase 4 — switch fourni par EXYTE, pose et paramétrage PROSYB | C65: VDI | D65: VDI-50 | E65: OCTET PLUS / LIEN'K | F65: BAI4288CN | G65: MO : Par répartiteur : pose baie 42U + équipement + switchs EXYTE | Fourniture Octet Plus devis DE044128 du 15/10/2026 (ZVK EasyLan, garantie système 25 ans ; baies LIEN'K), par répartiteur : baie 42U 800×800 + bandeau 8 PC = 634.85 €. Switchs fournis par EXYTE. | H65: u | I65: 2 | J65: 634.85 | K65: =J65*$I65 | M65: =L65*$I65 | N65: 5 | O65: =N65*$I65 | Q65: =P65*$I65 | R65: =$L65*$M$14+$N65*$O$14+$P65*$Q$14 | S65: =R65*$I65 | T65: =$S65+$K65 | U65: =HLOOKUP($C65,Recap_FCI!$K$9:$S$20,11,FALSE) | V65: =HLOOKUP($C65,Recap_FCI!$K$9:$S$20,12,FALSE) | W65: =$J65*$U65 | X65: =$R65*$V65 | Y65: =X65+W65 | Z65: =$W65*$I65 | AA65: =$X65*$I65 | AB65: =$Y65*$I65
A66: 3.8 | B66: Fourniture, pose et raccordement liaisons RJ45 CAT6A F/STP répartiteur informatique secondaire vers équipements (postes de travail CAD + bornes WiFi), 18 prises RJ45 par îlot, soit 360 prises RJ45 | C66: VDI | D66: VDI-00 | E66: OCTET PLUS / ZVK | F66: ZVKCEFF1212K | G66: MO : 360 liens × 1,2 h | Fourniture Octet Plus devis DE044128 du 15/10/2026 (ZVK EasyLan, garantie système 25 ans ; baies LIEN'K), 360 liens Cat. 6A F/FTP ≈ 35 m, même composition = 11561.43 €. Pose cuivre non incluse : MO PROSYB à ajouter. | H66: ens | I66: 1 | J66: 11561.43 | K66: =J66*$I66 | L66: 432 | M66: =L66*$I66 | O66: =N66*$I66 | Q66: =P66*$I66 | R66: =$L66*$M$14+$N66*$O$14+$P66*$Q$14 | S66: =R66*$I66 | T66: =$S66+$K66 | U66: =HLOOKUP($C66,Recap_FCI!$K$9:$S$20,11,FALSE) | V66: =HLOOKUP($C66,Recap_FCI!$K$9:$S$20,12,FALSE) | W66: =$J66*$U66 | X66: =$R66*$V66 | Y66: =X66+W66 | Z66: =$W66*$I66 | AA66: =$X66*$I66 | AB66: =$Y66*$I66
A67: 3.9 | B67: Pose et raccordement borne WiFi | C67: VDI | D67: CFA-95 | G67: MO : 60 bornes × (0,75 h + 0,25 h) | | H67: u | I67: 60 | K67: =J67*$I67 | L67: 0.75 | M67: =L67*$I67 | N67: 0.25 | O67: =N67*$I67 | Q67: =P67*$I67 | R67: =$L67*$M$14+$N67*$O$14+$P67*$Q$14 | S67: =R67*$I67 | T67: =$S67+$K67 | U67: =HLOOKUP($C67,Recap_FCI!$K$9:$S$20,11,FALSE) | V67: =HLOOKUP($C67,Recap_FCI!$K$9:$S$20,12,FALSE) | W67: =$J67*$U67 | X67: =$R67*$V67 | Y67: =X67+W67 | Z67: =$W67*$I67 | AA67: =$X67*$I67 | AB67: =$Y67*$I67
A68: 3.10 | B68: Recettage cuivre | C68: VDI | D68: DIV-80 | G68: MO : Certification 360 liens × 0,1 h + rapports 2 h | Certification cuivre non chiffrée par Octet Plus. | H68: ens | I68: 1 | K68: =J68*$I68 | M68: =L68*$I68 | N68: 38 | O68: =N68*$I68 | Q68: =P68*$I68 | R68: =$L68*$M$14+$N68*$O$14+$P68*$Q$14 | S68: =R68*$I68 | T68: =$S68+$K68 | U68: =HLOOKUP($C68,Recap_FCI!$K$9:$S$20,11,FALSE) | V68: =HLOOKUP($C68,Recap_FCI!$K$9:$S$20,12,FALSE) | W68: =$J68*$U68 | X68: =$R68*$V68 | Y68: =X68+W68 | Z68: =$W68*$I68 | AA68: =$X68*$I68 | AB68: =$Y68*$I68
AB70: =SUBTOTAL(9,AB57:AB68)
A71: 4 | B71: SÉCURITÉ SSI — PHASE 2 (2 MOIS) — TVA 20 %
A72: 4.1 | B72: Fourniture, pose et raccordement coffret report de contact SSI poste de garde principal | C72: SSI | D72: SSI-10 | G72: MO : Coffret de reports ≈ 30 contacts type SREI CA32 1 900 € (estimatif, prix budgétaire de repli) ; pose et câblage interne 4 h | | Heures technicien SSI comptées au taux technicien Cfa. | H72: ens | I72: 1 | J72: 1900 | K72: =J72*$I72 | M72: =L72*$I72 | N72: 4 | O72: =N72*$I72 | Q72: =P72*$I72 | R72: =$L72*$M$14+$N72*$O$14+$P72*$Q$14 | S72: =R72*$I72 | T72: =$S72+$K72 | U72: =HLOOKUP($C72,Recap_FCI!$K$9:$S$20,11,FALSE) | V72: =HLOOKUP($C72,Recap_FCI!$K$9:$S$20,12,FALSE) | W72: =$J72*$U72 | X72: =$R72*$V72 | Y72: =X72+W72 | Z72: =$W72*$I72 | AA72: =$X72*$I72 | AB72: =$Y72*$I72
A73: 4.2 | B73: Fourniture, pose et raccordement liaisons coffret report de contact SSI vers alarmes BAAS SSI îlots 1 et 2, poste de garde, poste énergie Hub 1 | C73: SSI | D73: SSI-00 | G73: MO : CR1-C1 estimatif : îlots 1-2 2 × 200 m 5G1,5 (2,90 €/m) + Hub 1 220 m et Hub 2 450 m 7G1,5 (4,10 €/m) + PG 10 m ; tirage 1 080 m à 3 h/100 m + 5 raccordements | | Heures technicien SSI comptées au taux technicien Cfa. | H73: ens | I73: 1 | J73: 3948 | K73: =J73*$I73 | L73: 32.4 | M73: =L73*$I73 | N73: 5 | O73: =N73*$I73 | Q73: =P73*$I73 | R73: =$L73*$M$14+$N73*$O$14+$P73*$Q$14 | S73: =R73*$I73 | T73: =$S73+$K73 | U73: =HLOOKUP($C73,Recap_FCI!$K$9:$S$20,11,FALSE) | V73: =HLOOKUP($C73,Recap_FCI!$K$9:$S$20,12,FALSE) | W73: =$J73*$U73 | X73: =$R73*$V73 | Y73: =X73+W73 | Z73: =$W73*$I73 | AA73: =$X73*$I73 | AB73: =$Y73*$I73
A74: 4.3 | B74: Fourniture, pose et raccordement centrale type 3 SSI poste de garde, y compris déclencheurs manuels et sirenes | C74: SSI | D74: SSI-10 | E74: AVISS | F74: AE2610CO901 | G74: MO : Pose centrale type 3 + DM + télécommande, câblage | Fourniture seule AVISS devis AE2610CO901 v2 du 13/10/2026 : CONCEPT 3 (177 €) + 1 DM 4710R1 (23,40 €) + capot CPDM (4 €) + télécommande TMS-300 (98 €) + frais de port (25 €) - pose/câblage/MO à ajouter | Heures technicien SSI comptées au taux technicien Cfa. | H74: ens | I74: 1 | J74: 327.4 | K74: =J74*$I74 | M74: =L74*$I74 | N74: 4 | O74: =N74*$I74 | Q74: =P74*$I74 | R74: =$L74*$M$14+$N74*$O$14+$P74*$Q$14 | S74: =R74*$I74 | T74: =$S74+$K74 | U74: =HLOOKUP($C74,Recap_FCI!$K$9:$S$20,11,FALSE) | V74: =HLOOKUP($C74,Recap_FCI!$K$9:$S$20,12,FALSE) | W74: =$J74*$U74 | X74: =$R74*$V74 | Y74: =X74+W74 | Z74: =$W74*$I74 | AA74: =$X74*$I74 | AB74: =$Y74*$I74
A75: 4.4 | B75: Fourniture, pose et raccordement centrale type 3 SSI Poste Energie Hub 1, y compris déclencheurs manuels et sirenes | C75: SSI | D75: SSI-10 | E75: AVISS | F75: AE2610CO901 | G75: MO : Idem PG | Fourniture seule AVISS devis AE2610CO901 v2 du 13/10/2026 : CONCEPT 3 (177 €) + 1 DM 4710R1 (23,40 €) + capot CPDM (4 €) + télécommande TMS-300 (98 €) - pose/câblage/MO à ajouter | Heures technicien SSI comptées au taux technicien Cfa. | H75: ens | I75: 1 | J75: 302.4 | K75: =J75*$I75 | M75: =L75*$I75 | N75: 4 | O75: =N75*$I75 | Q75: =P75*$I75 | R75: =$L75*$M$14+$N75*$O$14+$P75*$Q$14 | S75: =R75*$I75 | T75: =$S75+$K75 | U75: =HLOOKUP($C75,Recap_FCI!$K$9:$S$20,11,FALSE) | V75: =HLOOKUP($C75,Recap_FCI!$K$9:$S$20,12,FALSE) | W75: =$J75*$U75 | X75: =$R75*$V75 | Y75: =X75+W75 | Z75: =$W75*$I75 | AA75: =$X75*$I75 | AB75: =$Y75*$I75
A76: 4.5 | B76: Fourniture, pose et raccordement centrale type 3 SSI Poste Energie Hub 2, y compris déclencheurs manuels et sirenes | C76: SSI | D76: SSI-10 | E76: AVISS | F76: AE2610CO901 | G76: MO : Idem + 2 DM supplémentaires | Fourniture seule AVISS devis AE2610CO901 v2 du 13/10/2026 : CONCEPT 3 (177 €) + 3 DM 4710R1 (70,20 €) + 3 capots CPDM (12 €) + télécommande TMS-300 (98 €) - pose/câblage/MO à ajouter | Heures technicien SSI comptées au taux technicien Cfa. | H76: ens | I76: 1 | J76: 357.2 | K76: =J76*$I76 | M76: =L76*$I76 | N76: 5 | O76: =N76*$I76 | Q76: =P76*$I76 | R76: =$L76*$M$14+$N76*$O$14+$P76*$Q$14 | S76: =R76*$I76 | T76: =$S76+$K76 | U76: =HLOOKUP($C76,Recap_FCI!$K$9:$S$20,11,FALSE) | V76: =HLOOKUP($C76,Recap_FCI!$K$9:$S$20,12,FALSE) | W76: =$J76*$U76 | X76: =$R76*$V76 | Y76: =X76+W76 | Z76: =$W76*$I76 | AA76: =$X76*$I76 | AB76: =$Y76*$I76
B77: HORS LOT — Fourniture, pose et raccordement centrale type 4 SSI Ilots 1 et 2, y compris déclencheurs manuels et sirenes
A78: 4.6 | B78: Fourniture, pose et raccordement déclencheurs manuels chantier | C78: SSI | D78: SSI-10 | E78: AVISS | F78: AE2610CO901 | G78: MO : 16 DM chantier : CR1-C1 2×1,5 ≈ 80 m/DM à 1,40 €/m (estimatif) ; tirage 1 280 m à 3 h/100 m (38,4 h) + pose 1 h/DM ; raccordement 0,5 h/DM | Fourniture seule AVISS devis AE2610CO901 v2 du 13/10/2026 : 16 DM étanches IP65 4713R1C avec capot à 86 € (implantation PROSYB : 4 accès, 4 zones, 8 en périphérie du bâtiment) - pose/câblage/MO à ajouter | Heures technicien SSI comptées au taux technicien Cfa. | H78: ens | I78: 1 | J78: 3168 | K78: =J78*$I78 | L78: 54.4 | M78: =L78*$I78 | N78: 8 | O78: =N78*$I78 | Q78: =P78*$I78 | R78: =$L78*$M$14+$N78*$O$14+$P78*$Q$14 | S78: =R78*$I78 | T78: =$S78+$K78 | U78: =HLOOKUP($C78,Recap_FCI!$K$9:$S$20,11,FALSE) | V78: =HLOOKUP($C78,Recap_FCI!$K$9:$S$20,12,FALSE) | W78: =$J78*$U78 | X78: =$R78*$V78 | Y78: =X78+W78 | Z78: =$W78*$I78 | AA78: =$X78*$I78 | AB78: =$Y78*$I78
A79: 4.7 | B79: Fourniture, pose et raccordement diffuseurs sonores chantier | C79: SSI | D79: SSI-10 | E79: AVISS | F79: AE2610CO901 | G79: MO : 12 diffuseurs : CR1-C1 3G1,5 ≈ 80 m à 1,90 €/m (estimatif) ; tirage 960 m (28,8 h) + pose sous abri 1 h/u ; raccordement 0,5 h/u | Fourniture seule AVISS devis AE2610CO901 v2 du 13/10/2026 : 12 équipements d'alarme sonores et lumineux CONCEPT 3 (BAAS Ma, IP45) à 177 € utilisés comme diffuseurs chantier - pose/câblage/MO à ajouter ; IP45 à protéger des intempéries (pose sous abri) | Heures technicien SSI comptées au taux technicien Cfa. | H79: ens | I79: 1 | J79: 3948 | K79: =J79*$I79 | L79: 40.8 | M79: =L79*$I79 | N79: 6 | O79: =N79*$I79 | Q79: =P79*$I79 | R79: =$L79*$M$14+$N79*$O$14+$P79*$Q$14 | S79: =R79*$I79 | T79: =$S79+$K79 | U79: =HLOOKUP($C79,Recap_FCI!$K$9:$S$20,11,FALSE) | V79: =HLOOKUP($C79,Recap_FCI!$K$9:$S$20,12,FALSE) | W79: =$J79*$U79 | X79: =$R79*$V79 | Y79: =X79+W79 | Z79: =$W79*$I79 | AA79: =$X79*$I79 | AB79: =$Y79*$I79
A80: 4.8 | B80: Paramétrage et mise en service | C80: SSI | D80: DIV-80 | G80: MO : Programmation centrales P2, essais avec PV ; BE : synoptique d'exécution, repérage, DOE SSI | | Heures technicien SSI comptées au taux technicien Cfa. | H80: ens | I80: 1 | K80: =J80*$I80 | M80: =L80*$I80 | N80: 8 | O80: =N80*$I80 | P80: 8 | Q80: =P80*$I80 | R80: =$L80*$M$14+$N80*$O$14+$P80*$Q$14 | S80: =R80*$I80 | T80: =$S80+$K80 | U80: =HLOOKUP($C80,Recap_FCI!$K$9:$S$20,11,FALSE) | V80: =HLOOKUP($C80,Recap_FCI!$K$9:$S$20,12,FALSE) | W80: =$J80*$U80 | X80: =$R80*$V80 | Y80: =X80+W80 | Z80: =$W80*$I80 | AA80: =$X80*$I80 | AB80: =$Y80*$I80
AB82: =SUBTOTAL(9,AB72:AB80)
A83: 5 | B83: SÉCURITÉ SSI — PHASE 3 (5 MOIS) — TVA 20 %
A84: 5.1 | B84: Fourniture, pose et raccordement liaisons coffret report de contact SSI vers centrales SSI îlots 3 à 10 | C84: SSI | D84: SSI-00 | G84: MO : Îlots 3-10 : 8 × ≈ 250 m 5G1,5 = 2 000 m à 2,90 €/m (estimatif) ; tirage 3 h/100 m + 8 raccordements | | Heures technicien SSI comptées au taux technicien Cfa. | H84: ens | I84: 1 | J84: 5800 | K84: =J84*$I84 | L84: 60 | M84: =L84*$I84 | N84: 8 | O84: =N84*$I84 | Q84: =P84*$I84 | R84: =$L84*$M$14+$N84*$O$14+$P84*$Q$14 | S84: =R84*$I84 | T84: =$S84+$K84 | U84: =HLOOKUP($C84,Recap_FCI!$K$9:$S$20,11,FALSE) | V84: =HLOOKUP($C84,Recap_FCI!$K$9:$S$20,12,FALSE) | W84: =$J84*$U84 | X84: =$R84*$V84 | Y84: =X84+W84 | Z84: =$W84*$I84 | AA84: =$X84*$I84 | AB84: =$Y84*$I84
B85: HORS LOT — Fourniture, pose et raccordement centrale type 4 SSI Ilots 3 à 10, y compris déclencheurs manuels et sirenes
A86: 5.2 | B86: Paramétrage et mise en service | C86: SSI | D86: DIV-80 | G86: MO : Essais reports îlots 3-10, PV ; mise à jour synoptique | | Heures technicien SSI comptées au taux technicien Cfa. | H86: ens | I86: 1 | K86: =J86*$I86 | M86: =L86*$I86 | N86: 6 | O86: =N86*$I86 | P86: 2 | Q86: =P86*$I86 | R86: =$L86*$M$14+$N86*$O$14+$P86*$Q$14 | S86: =R86*$I86 | T86: =$S86+$K86 | U86: =HLOOKUP($C86,Recap_FCI!$K$9:$S$20,11,FALSE) | V86: =HLOOKUP($C86,Recap_FCI!$K$9:$S$20,12,FALSE) | W86: =$J86*$U86 | X86: =$R86*$V86 | Y86: =X86+W86 | Z86: =$W86*$I86 | AA86: =$X86*$I86 | AB86: =$Y86*$I86
AB88: =SUBTOTAL(9,AB84:AB86)
A89: 6 | B89: SÉCURITÉ SSI — PHASE 4 (17 MOIS) — TVA 20 %
A90: 6.1 | B90: Fourniture, pose et raccordement centrale type 3 SSI Poste Energie Hub 3, y compris déclencheurs manuels et sirenes | C90: SSI | D90: SSI-10 | E90: AVISS | F90: AE2610CO901 | G90: MO : Pose centrale type 3 Hub 3 | Fourniture seule AVISS devis AE2610CO901 v2 du 13/10/2026 : CONCEPT 3 (177 €) + 1 DM 4710R1 (23,40 €) + capot CPDM (4 €) + télécommande TMS-300 (98 €) - pose/câblage/MO à ajouter | Heures technicien SSI comptées au taux technicien Cfa. | H90: ens | I90: 1 | J90: 302.4 | K90: =J90*$I90 | M90: =L90*$I90 | N90: 4 | O90: =N90*$I90 | Q90: =P90*$I90 | R90: =$L90*$M$14+$N90*$O$14+$P90*$Q$14 | S90: =R90*$I90 | T90: =$S90+$K90 | U90: =HLOOKUP($C90,Recap_FCI!$K$9:$S$20,11,FALSE) | V90: =HLOOKUP($C90,Recap_FCI!$K$9:$S$20,12,FALSE) | W90: =$J90*$U90 | X90: =$R90*$V90 | Y90: =X90+W90 | Z90: =$W90*$I90 | AA90: =$X90*$I90 | AB90: =$Y90*$I90
A91: 6.2 | B91: Fourniture, pose et raccordement liaisons coffret report de contact SSI vers alarmes Type 3 SSI îlots 1 à 20, poste énergie Hub 3 | C91: SSI | D91: SSI-00 | G91: MO : P4 estimatif : 3 câbles 7G1,5 × 400 m vers DC11 + 20 × 50 m 5G1,5 + Hub 3 300 m 7G1,5 ; tirage 2 500 m à 3 h/100 m + 20 raccordements | | Heures technicien SSI comptées au taux technicien Cfa. | H91: ens | I91: 1 | J91: 9050 | K91: =J91*$I91 | L91: 75 | M91: =L91*$I91 | N91: 20 | O91: =N91*$I91 | Q91: =P91*$I91 | R91: =$L91*$M$14+$N91*$O$14+$P91*$Q$14 | S91: =R91*$I91 | T91: =$S91+$K91 | U91: =HLOOKUP($C91,Recap_FCI!$K$9:$S$20,11,FALSE) | V91: =HLOOKUP($C91,Recap_FCI!$K$9:$S$20,12,FALSE) | W91: =$J91*$U91 | X91: =$R91*$V91 | Y91: =X91+W91 | Z91: =$W91*$I91 | AA91: =$X91*$I91 | AB91: =$Y91*$I91
B92: HORS LOT — Fourniture, pose et raccordement centrale type 3 SSI Ilots 1 à 20, y compris déclencheurs manuels et sirenes
A93: 6.3 | B93: Paramétrage et mise en service | C93: SSI | D93: DIV-80 | G93: MO : Programmation P4, essais 20 reports + Hub 3, PV ; BE : synoptique P4, DOE | | Heures technicien SSI comptées au taux technicien Cfa. | H93: ens | I93: 1 | K93: =J93*$I93 | M93: =L93*$I93 | N93: 8 | O93: =N93*$I93 | P93: 4 | Q93: =P93*$I93 | R93: =$L93*$M$14+$N93*$O$14+$P93*$Q$14 | S93: =R93*$I93 | T93: =$S93+$K93 | U93: =HLOOKUP($C93,Recap_FCI!$K$9:$S$20,11,FALSE) | V93: =HLOOKUP($C93,Recap_FCI!$K$9:$S$20,12,FALSE) | W93: =$J93*$U93 | X93: =$R93*$V93 | Y93: =X93+W93 | Z93: =$W93*$I93 | AA93: =$X93*$I93 | AB93: =$Y93*$I93
AB95: =SUBTOTAL(9,AB90:AB93)
A96: 7 | B96: VIDÉOSURVEILLANCE — PHASE 3 (5 MOIS) — TVA 20 %
B97: HORS LOT (lot GC) — Réalisation massif support candélabres pour mât caméra
A98: 7.1 | B98: Fourniture, pose et raccordement caméra fixe + mât (28 Caméras), avec maillage zone chantier + périphérie y compris intrusion marque HIKVISION | C98: CFA | D98: CFA-30 | E98: CCF / HIKVISION | F98: 313371 | G98: MO : Fourniture ajoutée : mât acier galva ≈ 6 m 300 €/u (estimatif, non chiffré au devis CCF ; massif au lot GC). MO : pose mât 1,5 h + caméra en hauteur 2,5 h + raccordement 0,5 h + 0,5 h (réf. ECLAIRION 2 h + 0,5 + 0,5) ; nacelle non comptée (hypothèse optimiste : nacelle chantier EXYTE) | Fourniture seule CCF devis 313371 du 12/10/2026 (caméra IP Bullet 4MP HIKVISION, 142,14€/u) - pose/mât/MO à ajouter | H98: u | I98: 28 | J98: 442.14 | K98: =J98*$I98 | L98: 4.5 | M98: =L98*$I98 | N98: 0.5 | O98: =N98*$I98 | Q98: =P98*$I98 | R98: =$L98*$M$14+$N98*$O$14+$P98*$Q$14 | S98: =R98*$I98 | T98: =$S98+$K98 | U98: =HLOOKUP($C98,Recap_FCI!$K$9:$S$20,11,FALSE) | V98: =HLOOKUP($C98,Recap_FCI!$K$9:$S$20,12,FALSE) | W98: =$J98*$U98 | X98: =$R98*$V98 | Y98: =X98+W98 | Z98: =$W98*$I98 | AA98: =$X98*$I98 | AB98: =$Y98*$I98
A99: 7.2 | B99: Fourniture, pose et raccordement liaison RJ45 CAT6A F/STP POE pour alimentation caméras + switchs industriels rail DIN de vidéoprotection dans coffrets de zone (coffrets fournis et posés par SPIE) | C99: CFA | D99: CFA-30 | E99: CCF | F99: 313371 | G99: MO : Fourniture ajoutée : 28 liaisons Cat. 6A extérieures ≈ 50 m à 1,70 €/m + connecteurs (estimatif). MO : 28 liaisons × 2 h + 8 coffrets × 2 h (switch, alim 48 V, boîtier optique) | Fourniture CCF devis 313371 du 12/10/2026 : 8 switchs industriels PoE rail DIN (3644,56€) + modules alim 48VDC (1874,88€) + boîtiers optiques rail DIN (307,68€) + modules SFP (870,48€). AUCUNE enveloppe/coffret extérieur à prévoir : coffret électrique fourni et posé par SPIE (lot élec, Ahmed 16/10/2026) ; PROSYB y amène fibre + liaisons caméras et installe le matériel. Pose/MO à ajouter. | H99: ens | I99: 1 | J99: 9413.6 | K99: =J99*$I99 | L99: 56 | M99: =L99*$I99 | N99: 16 | O99: =N99*$I99 | Q99: =P99*$I99 | R99: =$L99*$M$14+$N99*$O$14+$P99*$Q$14 | S99: =R99*$I99 | T99: =$S99+$K99 | U99: =HLOOKUP($C99,Recap_FCI!$K$9:$S$20,11,FALSE) | V99: =HLOOKUP($C99,Recap_FCI!$K$9:$S$20,12,FALSE) | W99: =$J99*$U99 | X99: =$R99*$V99 | Y99: =X99+W99 | Z99: =$W99*$I99 | AA99: =$X99*$I99 | AB99: =$Y99*$I99
A100: 7.3 | B100: Enregistreur NVR marque HIKVISION | C100: CFA | D100: CFA-30 | E100: CCF / HIKVISION | F100: 313371 | G100: MO : Pose NVR + disque en baie Hub 1 | Fourniture CCF devis 313371 du 12/10/2026 : NVR 32 canaux (706,67€) + HDD 20TB (1545,45€) | H100: ens | I100: 1 | J100: 2252.12 | K100: =J100*$I100 | M100: =L100*$I100 | N100: 3 | O100: =N100*$I100 | Q100: =P100*$I100 | R100: =$L100*$M$14+$N100*$O$14+$P100*$Q$14 | S100: =R100*$I100 | T100: =$S100+$K100 | U100: =HLOOKUP($C100,Recap_FCI!$K$9:$S$20,11,FALSE) | V100: =HLOOKUP($C100,Recap_FCI!$K$9:$S$20,12,FALSE) | W100: =$J100*$U100 | X100: =$R100*$V100 | Y100: =X100+W100 | Z100: =$W100*$I100 | AA100: =$X100*$I100 | AB100: =$Y100*$I100
A101: 7.4 | B101: Paramétrage / Logiciel (analyse comportementale et port des EPI, intrusion périphérique) | C101: CFA | D101: CFA-40 | E101: CCF | F101: 313371 | G101: MO : Paramétrage NVR/iVMS 8 h + 28 caméras × 1 h (analyse intrusion/EPI) (réf. ECLAIRION 1,5 h/cam, optimisé) ; BE : étude de couverture, zones, RGPD 16 h + DOE 4 h | Fourniture CCF devis 313371 du 12/10/2026 : unité de supervision PCAM Inspiron 13 (933,77€) | H101: ens | I101: 1 | J101: 933.77 | K101: =J101*$I101 | M101: =L101*$I101 | N101: 36 | O101: =N101*$I101 | P101: 20 | Q101: =P101*$I101 | R101: =$L101*$M$14+$N101*$O$14+$P101*$Q$14 | S101: =R101*$I101 | T101: =$S101+$K101 | U101: =HLOOKUP($C101,Recap_FCI!$K$9:$S$20,11,FALSE) | V101: =HLOOKUP($C101,Recap_FCI!$K$9:$S$20,12,FALSE) | W101: =$J101*$U101 | X101: =$R101*$V101 | Y101: =X101+W101 | Z101: =$W101*$I101 | AA101: =$X101*$I101 | AB101: =$Y101*$I101
A102: 7.5 | B102: Recettage cuivre | C102: CFA | D102: DIV-80 | G102: MO : Recette 28 liaisons × 0,1 h + PV 2 h | | H102: ens | I102: 1 | K102: =J102*$I102 | M102: =L102*$I102 | N102: 5 | O102: =N102*$I102 | Q102: =P102*$I102 | R102: =$L102*$M$14+$N102*$O$14+$P102*$Q$14 | S102: =R102*$I102 | T102: =$S102+$K102 | U102: =HLOOKUP($C102,Recap_FCI!$K$9:$S$20,11,FALSE) | V102: =HLOOKUP($C102,Recap_FCI!$K$9:$S$20,12,FALSE) | W102: =$J102*$U102 | X102: =$R102*$V102 | Y102: =X102+W102 | Z102: =$W102*$I102 | AA102: =$X102*$I102 | AB102: =$Y102*$I102
AB104: =SUBTOTAL(9,AB97:AB102)
A105: 8 | B105: GTB / GTE (offre Aetherys attendue — provisoire) — TVA 20 %
A106: 8.1 | B106: Fourniture, pose et raccordement automate WAGO avec interface Ethernet modbus TCP/IP TGBT Hub 1, Hub 2 et Hub 3 | C106: CFA | D106: CVC-60 | E106: WAGO (provisoire) | F106: 751-9301 | G106: MO : PROVISOIRE (offre Aetherys attendue) : WAGO CC100 751-9301 580 € + 2 modules 16 entrées ≈ 120 € (estimatif) ; pose en TGBT 3 h | | H106: u | I106: 3 | J106: 820 | K106: =J106*$I106 | M106: =L106*$I106 | N106: 3 | O106: =N106*$I106 | Q106: =P106*$I106 | R106: =$L106*$M$14+$N106*$O$14+$P106*$Q$14 | S106: =R106*$I106 | T106: =$S106+$K106 | U106: =HLOOKUP($C106,Recap_FCI!$K$9:$S$20,11,FALSE) | V106: =HLOOKUP($C106,Recap_FCI!$K$9:$S$20,12,FALSE) | W106: =$J106*$U106 | X106: =$R106*$V106 | Y106: =X106+W106 | Z106: =$W106*$I106 | AA106: =$X106*$I106 | AB106: =$Y106*$I106
A107: 8.2 | B107: Fourniture, pose et raccordement alimentation automate WAGO | C107: CFA | D107: CVC-60 | G107: MO : PROVISOIRE : alimentation 24 V 787-1622 150 € ; pose 0,5 h (réf. SAFRAN) | | H107: u | I107: 3 | J107: 150 | K107: =J107*$I107 | M107: =L107*$I107 | N107: 0.5 | O107: =N107*$I107 | Q107: =P107*$I107 | R107: =$L107*$M$14+$N107*$O$14+$P107*$Q$14 | S107: =R107*$I107 | T107: =$S107+$K107 | U107: =HLOOKUP($C107,Recap_FCI!$K$9:$S$20,11,FALSE) | V107: =HLOOKUP($C107,Recap_FCI!$K$9:$S$20,12,FALSE) | W107: =$J107*$U107 | X107: =$R107*$V107 | Y107: =X107+W107 | Z107: =$W107*$I107 | AA107: =$X107*$I107 | AB107: =$Y107*$I107
A108: 8.3 | B108: Fourniture, pose et raccordement liaison WAGO vers switch GTB | C108: CFA | D108: CVC-60 | G108: MO : Cordon/liaison Cat. 6A vers switch terrain | | H108: u | I108: 3 | J108: 30 | K108: =J108*$I108 | L108: 1 | M108: =L108*$I108 | O108: =N108*$I108 | Q108: =P108*$I108 | R108: =$L108*$M$14+$N108*$O$14+$P108*$Q$14 | S108: =R108*$I108 | T108: =$S108+$K108 | U108: =HLOOKUP($C108,Recap_FCI!$K$9:$S$20,11,FALSE) | V108: =HLOOKUP($C108,Recap_FCI!$K$9:$S$20,12,FALSE) | W108: =$J108*$U108 | X108: =$R108*$V108 | Y108: =X108+W108 | Z108: =$W108*$I108 | AA108: =$X108*$I108 | AB108: =$Y108*$I108
A109: 8.4 | B109: Fourniture, pose et raccordement liaison interne contacts SD vers automate WAGO dans les TGBT Hub 1, Hub 2 et Hub 3 | C109: CFA | D109: CVC-60 | G109: MO : ≈ 20 contacts SD/TOR par TGBT × 0,25 h + contrôle ; fils et borniers 80 € | | H109: u | I109: 3 | J109: 80 | K109: =J109*$I109 | L109: 5 | M109: =L109*$I109 | N109: 1 | O109: =N109*$I109 | Q109: =P109*$I109 | R109: =$L109*$M$14+$N109*$O$14+$P109*$Q$14 | S109: =R109*$I109 | T109: =$S109+$K109 | U109: =HLOOKUP($C109,Recap_FCI!$K$9:$S$20,11,FALSE) | V109: =HLOOKUP($C109,Recap_FCI!$K$9:$S$20,12,FALSE) | W109: =$J109*$U109 | X109: =$R109*$V109 | Y109: =X109+W109 | Z109: =$W109*$I109 | AA109: =$X109*$I109 | AB109: =$Y109*$I109
A110: 8.5 | B110: Fourniture, pose et raccordement liaison interne compteur d'énergie TGBT Hub 1, 2 et 3 vers automate WAGO | C110: CFA | D110: CVC-60 | G110: MO : Bus RS485 2 compteurs ≈ 30 m (0,07 h/ml, réf. SAFRAN) + raccordement | | H110: u | I110: 3 | J110: 40 | K110: =J110*$I110 | L110: 2 | M110: =L110*$I110 | N110: 1 | O110: =N110*$I110 | Q110: =P110*$I110 | R110: =$L110*$M$14+$N110*$O$14+$P110*$Q$14 | S110: =R110*$I110 | T110: =$S110+$K110 | U110: =HLOOKUP($C110,Recap_FCI!$K$9:$S$20,11,FALSE) | V110: =HLOOKUP($C110,Recap_FCI!$K$9:$S$20,12,FALSE) | W110: =$J110*$U110 | X110: =$R110*$V110 | Y110: =X110+W110 | Z110: =$W110*$I110 | AA110: =$X110*$I110 | AB110: =$Y110*$I110
A111: 8.6 | B111: Fourniture, pose et raccordement ordinateur fixe avec 2 écrans au niveau du poste de garde | C111: CFA | D111: CVC-60 | E111: DELL (provisoire) | G111: MO : PROVISOIRE : PC fixe + 2 écrans 24" 1 150 € (prix budgétaire de repli) ; installation 3 h | | H111: u | I111: 1 | J111: 1150 | K111: =J111*$I111 | M111: =L111*$I111 | N111: 3 | O111: =N111*$I111 | Q111: =P111*$I111 | R111: =$L111*$M$14+$N111*$O$14+$P111*$Q$14 | S111: =R111*$I111 | T111: =$S111+$K111 | U111: =HLOOKUP($C111,Recap_FCI!$K$9:$S$20,11,FALSE) | V111: =HLOOKUP($C111,Recap_FCI!$K$9:$S$20,12,FALSE) | W111: =$J111*$U111 | X111: =$R111*$V111 | Y111: =X111+W111 | Z111: =$W111*$I111 | AA111: =$X111*$I111 | AB111: =$Y111*$I111
A112: 8.7 | B112: Paramétrage / Logiciel avec historisation (Licence, dashboards consos, alertes SMS/Mail) | C112: CFA | D112: DIV-70 | G112: MO : PROVISOIRE : passerelle SMS 4G 250 € (estimatif), logiciel de supervision sans licence ; programmation 3 automates × 8 h + supervision/dashboards 12 h + essais point à point 4 h ; BE : liste des points, analyse fonctionnelle, DOE | | H112: ens | I112: 1 | J112: 250 | K112: =J112*$I112 | M112: =L112*$I112 | N112: 40 | O112: =N112*$I112 | P112: 16 | Q112: =P112*$I112 | R112: =$L112*$M$14+$N112*$O$14+$P112*$Q$14 | S112: =R112*$I112 | T112: =$S112+$K112 | U112: =HLOOKUP($C112,Recap_FCI!$K$9:$S$20,11,FALSE) | V112: =HLOOKUP($C112,Recap_FCI!$K$9:$S$20,12,FALSE) | W112: =$J112*$U112 | X112: =$R112*$V112 | Y112: =X112+W112 | Z112: =$W112*$I112 | AA112: =$X112*$I112 | AB112: =$Y112*$I112
AB114: =SUBTOTAL(9,AB106:AB112)
K115: =SUBTOTAL(9,K18:K114) | M115: =SUBTOTAL(9,M18:M114) | O115: =SUBTOTAL(9,O18:O114) | Q115: =SUBTOTAL(9,Q18:Q114) | S115: =SUBTOTAL(9,S18:S114) | T115: =SUBTOTAL(9,T18:T114)
A116: TOTAL GÉNÉRAL HORS TAXES | Z116: =SUBTOTAL(9,Z18:Z115) | AA116: =SUBTOTAL(9,AA18:AA115) | AB116: =SUBTOTAL(9,AB18:AB115)
...

Sheet CGV PROSYB
A2: CONDITIONS GENERALES DE VENTE Edition 01 2025
A4: 1. Définitions | C4: le Fournisseur pourra résilier le Contrat sans préavis par l’envoi d’une lettre RAR adressée au Client,
C5: sans préjudice d’une demande d’indemnisation.
A6: « Date d’établissement des prix » désigne la date d’établissement des prix mentionnée
A7: sur la proposition commerciale du Fournisseur ou à défaut, la date d’émission de cette | C7: 5. Interruption et Modification
A8: proposition commerciale ou à défaut, la date de la première signature des Conditions
A9: Particulières. | C9: 5.1 Le Fournisseur se réserve le droit d’interrompre la commercialisation, à tout
A10: « Client » désigne le co-contractant du Fournisseur dont les références sont précisées | C10: moment, de l’un ou de plusieurs de ses Livrables et des Prestations; une telle
A11: dans les Conditions Particulières. Si ces dernières désignent comme bénéficiaire des | C11: interruption ne remettant toutefois pas en cause la fourniture de Livrables et/ou
A12: Livrables et/ou Prestations une entité juridique autre que le signataire, le terme Client sera | C12: Prestations préalablement acceptés par les Parties.
A13: étendu à cette entité juridique. | C13: 5.2 Du fait de l’évolution rapide des technologies, le Fournisseur se réserve le droit de
A14: « Conditions Générales » désignent le présent document. | C14: fournir au Client des Livrables différents de ceux commandés à condition qu’une telle
A15: « Conditions Particulières » désignent le document signé par les Parties (ou à défaut la | C15: substitution ne conduise à aucune altération des qualités inhérentes au Livrable
A16: proposition du Fournisseur acceptée par le Client selon les stipulations des présentes) | C16: initialement prévues et sans que le Contrat ne puisse donner lieu à résolution ou à
A17: précisant notamment les Livrables, les prix et les Prestations éventuellement souscrites | C17: réfaction.
A18: par le Client.
A19: « Constructeurs » désignent le(s) fabricant(s) des Matériels et/ou le(s) éditeurs des | C19: 6. Propriété Intellectuelle
A20: Logiciels.
A21: « Contrat » désigne les Conditions Générales et les Conditions Particulières. | C21: 6.1 Tous plans, dessins, méthodes, concepts, savoir-faire, techniques, textes, schémas
A22: « Développement Spécifique » désigne tout développement logiciel réalisé par le | C22: et en général tous documents relatifs à la conception, à la construction, à l’exécution ou
A23: Fournisseur pour répondre à un besoin fonctionnel spécifique du Client lequel déclare | C23: mise en œuvre des Livrables, toutes mises à jour, copies de Livrables, ainsi que tous
A24: détenir les accords et droits nécessaires du titulaire d’un logiciel ou progiciel préexistant | C24: renseignements d’ordre technique ou commercial fournis à l’occasion de la proposition
A25: pour réaliser ledit développement. Les Développements Spécifiques sont régis par la | C25: commerciale et/ou du Contrat demeurent la propriété du Fournisseur et/ou de ses
A26: Licence d’Utilisation du Fournisseur en vigueur. | C26: Constructeurs et ne pourront être reproduits ou communiqués aux tiers sans l’accord
A27: « Equipement » désigne tout Matériel et/ou Logiciel acheté(s) par le Client auprès du | C27: préalable écrit du Fournisseur et/ou de ses Constructeurs.
A28: Fournisseur ainsi que leur documentation associée, tels que listés limitativement dans les | C28: 6.2 Tous droits de propriété intellectuelle attachés aux Livrables restent la propriété
A29: Conditions Particulières. | C29: entière et exclusive du Fournisseur et/ou des Constructeurs, le Client ne bénéficiant que
A30: « Fournisseur » désigne la Société dont les coordonnées sont précisées aux Conditions | C30: des droits concédés sur les dits Livrables au titre des licences accordées par le
A31: Particulières ou au Bon de Commande. Le Fournisseur peut être PROSYB ou l’une de ses sociétés | C31: Fournisseur et/ou les Constructeurs dont il déclare avoir pris connaissance et en
A32: Particulières ou au Bon de Commande. Le Fournisseur peut être PROSYB ou l’une de ses sociétés | B32: Installation CloudLink | C32: Fournisseur et/ou les Constructeurs dont il déclare avoir pris connaissance et en | F32: 1
A33: affiliées (« Société Affiliée » signifie toute entité juridique qui contrôle, est contrôlée ou est | C33: respecter l’intégralité des termes. En tout état de cause, le Client reconnaît que le
A34: sous le même contrôle qu’une des Parties au sens de l’article L.233-16 du Code de | C34: Fournisseur ne peut accorder plus de droits qu’il n’en a reçus du Constructeur.
A35: commerce.) | C35: Sous réserve de ses droits et de ceux des tiers qui lui sont octroyés dans les conditions
A36: « Livrable » désigne les Développements Spécifiques, les Equipements et les Modules | C36: strictes des licences concernées, le Fournisseur consentira au Client une licence non-
A37: Logiciels. | C37: exclusive d’utilisation des Livrables en France métropolitaine, selon leurs destinations,
A38: « Logiciel » désigne l’ensemble des programmes informatiques, procédés, règles de langage et la | C38: pour les seuls besoins personnels du Client et pour la durée spécifiée dans la licence
A39: documentation éventuelle, sous forme de code objet, relatifs au fonctionnement d’un ensemble | C39: concernée. Cette licence ne conférera pas au Client le droit:
A40: de traitement de données pour une machine, fournis sur une bande magnétique ou sur tout autre | C40: (i) de sous-licencier les Livrables;
A41: support de stockage présent ou à venir. | C41: (ii) de modifier ou de faire modifier par un tiers lesdits Livrables ;
A42: « Matériel » désigne l’intégralité des ensembles et sous-ensembles composés d’éléments | C42: (iii) de copier ou de reproduire les Livrables à l’exception d’une copie dite de
A43: physiques (PBX ou autocommutateurs, serveurs associés, éléments passifs et actifs de | C43: (iv) “sauvegarde”. Toute copie devra porter la mention du droit de copyright du
A44: réseaux informatiques, terminaux téléphoniques, terminaux informatiques, | C44: (v)Fournisseur et/ou de(s) Constructeur(s) des Livrables copiés ;
... A55: en service et l’activité principale du Client. | C55: tribunal viendrait à juger de façon définitive qu’un Livrable contrefait un droit de propriété
C56: intellectuelle appartenant à un tiers, le Fournisseur aura le choix entre l’une des solutions
A57: 2. Objet des Conditions Générales de Vente | C57: suivantes :
C58: (i) obtenir à ses frais le droit pour le Client de continuer à utiliser les Livrables ;
A59: 2.1 Les Conditions Générales régissent toutes les relations commerciales contractuelles | C59: (ii) substituer aux Livrables incriminés des livrables non contrefaisants équivalents ;
A60: ou précontractuelles entre le Fournisseur et le Client relatives à la fourniture de Livrables, | C60: (iii) modifier les Livrables incriminés afin qu’ils ne soient plus en infraction ;
A61: avec ou sans Prestation. Les autres services proposés par le Fournisseur seront régis par | C61: (iv) résilier le Contrat et reprendre au Client les Livrables incriminés à un prix égal à celui
A62: les conditions générales de services en vigueur chez le Fournisseur. | C62: (v) auquel ils ont été achetés, diminué d’un montant déterminé par le Fournisseur en
A63: 2.2 L’acceptation des Conditions Particulières par le Client implique son adhésion aux | C63: (vi) fonction de leur dépréciation, sous réserve que les Livrables incriminés soient
A64: Conditions Générales ; étant précisé que toutes les clauses dérogatoires ou | C64: (vii) retournés au Fournisseur.
A65: complémentaires au Contrat seront d’interprétation strictes et devront pour être valables, | C65: Sauf dispositions légales contraires, l’indemnisation du Client ne pourra dépasser dix
A66: être préalablement acceptées par écrit par le Fournisseur. | C66: pour cent du prix des Livrables objets d’une action en revendication au titre du droit de
A67: 2.3 Le Contrat est constitué des Conditions Particulières et des Conditions Générales, les | C67: propriété intellectuelle.
A68: Conditions Particulières prévalant sur les Conditions Générales. Le Contrat constitue | C68: 6.4 Le Client s’engage à obtenir l’accord préalable et écrit du Fournisseur pour toute
A69: l’intégralité des documents contractuels faisant foi entre les Parties. Le Contrat annule et | C69: opération de cession ou transfert des Livrables, qu’elle soit à titre onéreux ou gracieux,
A70: remplace toute disposition écrite qui figurerait sur tout autre document, convention | C70: et d’obtenir de son acheteur le respect des obligations qu’il a prises envers le
A71: antérieure, conditions générales du Client, se rapportant au même objet. | C71: Fournisseur au titre du présent article.
A72: 2.4 Le Fournisseur se réserve le droit de modifier à tout moment le contenu de ses
A73: Conditions Générales. De telles modifications donnent lieu à l’édition d’une nouvelle | C73: 7. Délais- Plage horaire d’exécution des Prestations
A74: version qui s’applique aux Contrats conclus après cette édition.
C75: 7.1 Le Fournisseur s’engage à fournir ses meilleurs efforts pour respecter les délais. Les
A76: 3. Informations relatives aux livrables- Pré-requis | C76: 7.2 délais ne commencent à courir qu’à compter du plus tardif des événements
C77: 7.3 suivants : (i) la date de réception par le Fournisseur du Contrat dûment signé par le
A78: Le Client reconnaît qu’il a, préalablement au Contrat, fourni au Fournisseur toutes | C78: 7.4 Client (ii) ou de la date de prise d’effet du Contrat (iii) ou du paiement éventuellement
A79: informations utiles à la compréhension de ses besoins et à l’exécution du Contrat. Le | C79: 7.5 exigible à la passation du Contrat (iv) ou de l’accord de financement nécessaire le
A80: Fournisseur ne pourra en aucune manière être tenue responsable des conséquences | C80: 7.6 cas échéant. Les délais de livraison et d’installation sont des délais indicatifs.
A81: d’une absence d’information de la part du Client ou de l’inexactitude des informations qui | C81: 7.7 Le Fournisseur ne sera pas tenu responsable de tout retard d’exécution dans les
A82: lui auraient été données par le Client. | C82: 7.8 hypothèses suivantes:
A83: Le Client reconnaît avoir été informé et avoir pris connaissance des spécifications | C83: (i) si les renseignements (notamment le(s) document(s) de paramétrage), documents
A84: techniques des Livrables et assume la responsabilité de ses choix en fonction de ses | C84: ou prestations dont la fourniture incombe au Client ne sont pas exhaustifs ou fournis
A85: capacités et de ses besoins. Il reconnaît avoir reçu toute information nécessaire à cet | C85: en temps voulu. Ceci inclut notamment l’ensemble des informations techniques
A86: égard. Le Client reconnaît que le bon fonctionnement des Livrables nécessite que ceux-ci | C86: nécessaires au Fournisseur en cas de réutilisation, dans la configuration vendue,
A87: soient installés dans un environnement physique adapté. Il est de la responsabilité du | C87: des équipements existants ;
A88: Client de fournir un environnement répondant aux exigences ou pré-requis pour lesdits | C88: (ii) en cas de force majeure ou d’événements échappant au contrôle et à la
A89: Livrables et de mettre à disposition du Fournisseur des locaux non affectés par le | C89: responsabilité du Fournisseur, de ses Constructeurs et/ou des transporteurs ;
... A94: Les Livrables et Prestations sont limitativement listées dans les Conditions Particulières. | C94: (v) en cas de non respect des conditions d’environnement et de mise en service dont le
C95: Client est réputé avoir connaissance ;
A96: 4. Financement par un organisme spécialisé | C96: (vi) en cas de modification du fait du Client dans le volume ou la nature ou les conditions
C97: d’exécution de fourniture des Livrables et/ou des Prestations;
A98: Si les Livrables (et éventuellement les Prestations) font l’objet d’une demande de | C98: (vii) au cas où les locaux dans lesquels les Prestations sont à exécuter présentent un
A99: financement par le Client auprès d’un organisme spécialisé, le Client devra le mentionner | C99: risque pour la santé au sens de la réglementation en vigueur. Aussi, le Fournisseur pourra
A100: dans les Conditions Particulières. En tout état de cause, le Contrat ayant été conclu de | C100: exiger que lui soit remis tous rapports et mesurages confirmant l'absence de risque. En
A101: façon ferme et définitive, le Client est tenu de respecter l’ensemble des droits et obligations | C101: pas de découverte imprévue de produits ou matériaux présentant des risques pour la
A102: nés du Contrat, y compris celle de payer le prix de vente des Livrables et des Prestations | C102: santé (ex : amiante), ou en cas de défaillance du Client ou de tiers à mettre en œuvre des
A103: comptant selon les conditions de facturation et de paiement énoncées aux Conditions Générales. | C103: mesures de protection appropriées, le Fournisseur se réserve le droit de suspendre
A104: A défaut d’avoir notifié au Fournisseur l’accord de financement ainsi obtenu dans un délai de trente | C104: l'exécution des Prestations dans l'attente de la définition et réalisation des mesures à
A105: jours calendaires à compter de la conclusion du Contrat (ou en cas de remise en cause du | C105: prendre par le Client pour maîtriser ce risque.
A106: financement ainsi obtenu), le Fournisseur pourra subordonner la poursuite du Contrat à la | C106: 7.3 Les Prestations (y compris la fourniture de Livrables) sont réalisées pendant les
A107: constitution à son profit, sous quinze jours calendaires, d’une garantie à première demande | C107: heures et jours ouvrés (du lundi au vendredi de 8h à 18h, hors jours fériés sauf dispositions
A108: émanant d’un établissement bancaire domicilié en France métropolitaine d’un montant égal | C108: contraires dans les Conditions Particulières). Les ajournements, séquencements,
A109: au montant du Contrat restant à encaisser. A défaut de cette remise dans le délai imparti, | C109: demandés par le Client pourront donner lieu à un supplément de prix.
A114: CONDITIONS GENERALES DE VENTE Edition 01 2025
A116: 8. Livraisons et Réclamations | C116: 11. Conditions d’Exploitation
A118: 8.1 Les Livrables sont livrés en France à l’adresse indiquée dans les Conditions Particulières. | C118: 11.1 La responsabilité du Fournisseur est strictement limitée aux Livrables et/ou
A119: 8.2 Le Client est tenu de vérifier l’état des colis livrés, la conformité du nombre et de la | C119: Prestations qui lui ont été confiés. Toute intervention ou modification sur les Livrables,
A120: contenance des colis avec les bordereaux d’expédition et de mentionner avec précision | C120: faite par un tiers dégagera toute responsabilité du Fournisseur.
A121: ses réserves, par lettre recommandée avec accusé réception, dans les trois jours suivant | C121: 11.2 Le Fournisseur dégage toute responsabilité à raison des incidences techniques
A122: la livraison desdits Livrables. | C122: notamment des effets parasitaires provoquées de façon directe ou indirecte par du
...

Sheet FAMILLE
A1: LOT FAM | B1: NOM FAMILLE
A2: AUT-00 | B2: Chemins de cables, Cablofil et accessoires
A3: AUT-10 | B3: Mise à la terre
A4: AUT-20 | B4: Etiquettage, repérage
A5: AUT-30 | B5: Consommables
A6: AUT-40 | B6: Boitiers alu, boitiers de sol
A7: AUT-50 | B7: Goulottes, moulures, plinthes électriques, tube IRO, Gaine ICT, boites de dérivation …
A8: AUT-60
A9: AUT-70
A10: AUT-80
A11: AUT-90
A12: VDI-00 | B12: Cables 4p
A13: VDI-10 | B13: Multipaire Téléphone
A14: VDI-20 | B14: Fibres Optiques Cables, connecteurs et accessoires
A15: VDI-30 | B15: Noyaux et accessoires de prise
A16: VDI-40 | B16: Platines 19"
A17: VDI-50 | B17: Baies, Coffrets, Fermes et accessoires
A18: VDI-60 | B18: Solution de Gestion de Câblage
A19: VDI-70 | B19: Cordons de brassage, jarretières optiques
A20: VDI-80
A21: VDI-90
A22: CFA-00 | B22: Câblage Cfa
A23: CFA-10 | B23: Equipements Contrôle d'accès
A24: CFA-20 | B24: Applications de Contrôle d'accès
A25: CFA-30 | B25: Equipements Vidéo Surveillance
A26: CFA-40 | B26: Applications de Vidéo Surveillance
A27: CFA-50 | B27: Equipements Détection Intrusion
A28: CFA-60 | B28: Applications et centrale de Détection Intrusion
A29: CFA-70 | B29: Equipements Visiophonie, Interphonie
A30: CFA-80 | B30: Applications de Visiophonie, Interphonie
A31: CFA-90 | B31: Solution de Téléphonie (téléphone, PABX, périphériques …)
A32: CFA-95 | B32: Réseau informatique (Switch, média converter, routeur …)
A33: CFA-99 | B33: Serveurs, PC, Consoles, écran, imprimantes
... A36: SSI-20 | B36: EXTINCTION INCENDIE
A37: SSI-30
A38: SSI-40
A39: SSI-50
A40: SSI-60
A41: SSI-70
A42: SSI-80
A43: SSI-90
A44: CFO-00 | B44: Cables électrique
A45: CFO-10 | B45: Tableaux électriques
A46: CFO-20 | B46: Postes de transformation et Breakers
A47: CFO-30 | B47: Appareillage électrique, Prises de courant …
A48: CFO-40 | B48: Luminaires et lampes
A49: CFO-50 | B49: Générateurs et Moteurs électriques
A50: CFO-60 | B50: Eclairage de Sécurité
A51: CFO-70 | B51: Autres Equipements électriques
A52: CFO-80
A53: CFO-90
A54: CVC-00 | B54: PRODUCTION CHAUD/FROID
A55: CVC-01 | B55: CTA / EXTRACTEUR
A56: CVC-02 | B56: ROBINETTERIE
A57: CVC-03 | B57: POMPE DE CIRCULATION
A58: CVC-04 | B58: TUBE ACIER
A59: CVC-05 | B59: TUBE CUIVRE
A60: CVC-06 | B60: TUBE PVC
A61: CVC-07 | B61: CALORIFUGE TUBE
A62: CVC-08 | B62: DIVERS HYDRAULIQUE
A63: CVC-09
A64: CVC-10 | B64: GAINE
A65: CVC-11 | B65: CLAPET COUPE FEU
A66: CVC-12 | B66: ACOUSTIQUE
A67: CVC-13 | B67: GRILLES / DIFFUSEURS/ BOUCHES
A68: CVC-14 | B68: CALORIFUGE GAINE
A69: CVC-15 | B69: DIVERS AERAULIQUE
A70: CVC-20 | B70: TERMINAUX PLOMBERIE
A71: CVC-21 | B71: TERMINAUX CHAUFFAGE
A72: CVC-22 | B72: TERMINAUX VENTILATION
A73: CVC-30 | B73: DEPOSE HYDRAULIQUE
A74: CVC-31 | B74: DEPOSE AERAULIQUE
A75: CVC-40 | B75: SECOND ŒUVRE
... A79: CVC-60 | B79: GTB / GTC
A80: CVC-70
A81: CVC-80
A82: CVC-90
A83: DIV-10 | B83: Déplacement, transport
A84: DIV-20 | B84: Base Vie
A85: DIV-30 | B85: Location outillage
A86: DIV-40 | B86: Manutention
A87: DIV-45 | B87: Mesure conservation, protection des ouvrages
A88: DIV-50 | B88: Pilotage, gouvernance projet
A89: DIV-60 | B89: Etudes, Plans d'installation, calculs
A90: DIV-70 | B90: Programmation, configuration
A91: DIV-80 | B91: Essais, Mise en Service
A92: DIV-85 | B92: Transfert de compétence, Formations
A93: DIV-90 | B93: Autocontrôles, Tests
B113: Pilotage, Gouvernance

Sheet REF
A1: Répertoire outils FCI | B1: c:\calcul\FCI | C1: Nom Feuille Modèle Bordereau | E1: Nom du Tarif | F1: Chemin complet vers le Fichier Base Tarif | H1: Vendeur | I1: Opérationnels | J1: Agences | K1: Offres | L1: Technologies
A2: Fichier modèles bordereau | B2: FCI_BORDEREAUX_SPIE.xlsx
A3: Figer Prix de Vente | B3: FALSE | C3: VDI Tertiaire | E3: VDI FLOW BUSINESS | F3: S:\DASCIO\Dpt-SIO\Communs\TARIFS\Tarif_VDI_Flow Business.xlsm | H3: Woody SEALE | I3: Woody SEALE | K3: VENTES NEUVES ET INSTALLATION | L3: CABLAGE & INFRASTRUCTURES VDI
A4: Index Tarif | C4: VDI DataCenter | E4: VDI COMMSCOPE | F4: S:\DASCIO\Dpt-SIO\Communs\TARIFS\Tarif_VDI_Commscope.xlsm | H4: YANDJA Palou | I4: YANDJA Palou | K4: NEGOCE | L4: SALLES INFORMATIQUES / LOCAUX SECURISES (LTS)
A5: Modele SPIE | C5: SURETE | E5: VDI NEXANS | F5: S:\DASCIO\Dpt-SIO\Communs\TARIFS\Tarif_VDI_Nexans.xlsm | H5: Jean-Miche BARBIER | I5: Jean-Miche BARBIER | K5: ADJONCTIONS / TRAVAUX | L5: ENERGIE & CLIMATISATION
A6: Répertoire installation | B6: \\ce\dfs-FI07\NATIONAL\Data-FTP\Basefc\DCE | C6: CFO Tertiaire | K6: TRAVAUX SUPPLEMENTAIRES (SUR AFFAIRE) | L6: SURETE (CONTRÔLE D'ACCES, GTC)
A7: Fichier Revue | B7: REVUE_OFFRE.xlsm | C7: CFO DataCenter | K7: DCR (PTVX, DEPANNAGE, Prestations au Ticket) | L7: VIDEO-PROTECTION ET IMAGERIE
A8: Fichier FDC | B8: Fiche de compte.xlsm | C8: CVC Tertiaire | K8: DEPLOIEMENT INDUSTRIEL (POSTES DE TRAVAIL, HORS OPERATEURS)
A9: Fichier Para User | B9: C:\calcul\annuaire\para_user.xls | C9: CVC DataCenter | K9: PROJET CLIENT SOUS CONTRAT INFOGERANCE | L9: RESEAUX LOCAUX FILAIRES
A10: Nom du Refnoms | B10: c:\calcul\refnoms\Refnoms_AX_DASCIO.xls | K10: DCR CLIENT SOUS CONTRAT INFOGERANCE | L10: RESEAUX LOCAUX SANS FIL (WIFI)
A11: ID Vendeur | K11: DEPLOIEMENT INDUSTRIEL CLIENT SOUS CONTRAT INFOGERANCE | L11: RESEAUX ETENDUS (WAN, MAN, FH)
A12: Nom du Vendeur | K12: TRAVAUX CLIENT SOUS CONTRAT INFOGERANCE | L12: RESEAUX D'OPERATEURS
A13: Tél Vendeur | K13: GOUVERNANCE I.T. (ETUDES) | L13: CPE OPERATEURS
A14: Email Vendeur | K14: ASSISTANCE A LA MISE EN ŒUVRE | L14: RESEAU CISCO
A15: Initiales Vendeur | K15: GESTION ET OPTIMISATION (INVENTAIRE, AUDITS…) | L15: RESEAU AVAYA
A16: Agence AX | K16: CONSEIL CLIENT SOUS CONTRAT INFOGERANCE | L16: RESEAU HP
A17: Adresse Agence | B17: 53, Bd de Stalingrad | L17: RESEAUX INDUSTRIELS ET EMBARQUES
A18: CP Agence | B18: 92247 | K18: MAINTIEN EN CONDITION OPERATIONNELLE (M.C.O.)
A19: Ville Agence | B19: Malakoff Cedex | K19: INFOGERANCE D'INFRASTRUCTURES (SUR SITE) | L19: SECURITE DES INFRASTRUCTURES ET TERMINAUX
A20: Direction Activité | B20: Direction des Activités Public et Industrie | K20: INFOGERANCE D'INFRASTRUCTURES (A DISTANCE) | L20: SECURITE ET PERFORMANCE DES APPLICATIONS
A21: Société | B21: SPIE ICS | K21: INFOGERANCE UTILISATEURS (SUR SITE)
A22: SIRET | B22: SAS au capital de 16.240.000 euros - RCS NANTERRE - SIRET 319 060 075 00813 - APE 6202A | K22: SERVICES D'INFOGERANCE UTILISATEURS (A DISTANCE) | L22: RESEAUX IP DU DATACENTER
K23: READOSSEMENT SUR CONTRAT | L23: SERVEURS
K24: INFOGERANCE GLOBALE (SUR SITE) | L24: STOCKAGE, ARCHIVAGE, RESTAURATION
K25: INFOGERANCE GLOBALE (A DISTANCE) | L25: POSTES DE TRAVAIL & PERIPHERIQUES BUREAUTIQUES
K26: LOGISTIQUE REPARATION | L26: VIRTUALISATION (SERVEURS, POSTES DE TRAVAIL)
K27: INFOGERANCE D'INFRASTRUCTURES (ASSISTANCE TECHNIQUE) | L27: APPLICATIONS D'ENTREPRISE (MESSAGERIE, ANNUAIRE…)
K28: INFOGERANCE UTILISATEURS (ASSISTANCE TECHNIQUE) | L28: APPLICATIONS D'ENTREPRISE (METIERS…)
K29: INFOGERANCE GLOBALE (ASSISTANCE TECHNIQUE)
A30: CGV | B30: CGV Multisociétés.pdf | L30: INFRASTRUCTURES DE TELEPHONIE (PABX, TOIP)
A31: Fichier Confo FCI | B31: FCI_CONFO.xlsm | K31: LIENS OPERATEURS VOIX (SC) | L31: VOIX AASTRA
A32: Manuel utilisation | B32: C:\calcul\FCI\Presentation_FCI.pdf | K32: LIENS OPERATEURS DATA (SC) | L32: VOIX CISCO
K33: DEPLOIEMENTS OPERATEURS SFR | L33: VOIX MITEL
K34: SERVICES MANAGES | L34: VOIX AVAYA
K35: SERVICES HEBERGES | L35: VOIX UNIFY
K36: SERVICES CLOUD | L36: TERMINAUX FIXES
K37: DEPLOIEMENTS OPERATEURS AUTRES | L37: TERMINAUX MOBILES & OUTILS DE NOMADISME
L38: OUTILS D'ADMIN. VOIX & TAXATION
K40: REVENUS OPERATEURS | L40: APPLI COMM UNIFIEE AASTRA
K41: REVISION DE PRIX & AUTRES REVENUS FINANCIERS | L41: APPLI COMM UNIFIEE CISCO
L42: APPLI COMM UNIFIEE MICROSOFT
K43: HORS REPORTING | L43: APPLI COMM UNIFIEE MITEL
L44: APPLI COMM UNIFIEE UNIFY
L45: APPLI COMM UNIFIEE AVAYA
L47: APPLI. CENTRES DE CONTACTS & SVI
L48: APPLI. DE MESSAGERIE (VOCALE / UNIFIEE)
L49: APPLI. VISIO/VIDEOCONFERENCE
L50: APPLI. DE COLLABORATION (AUTRES)
H93: OPERATIONNELS | I93: Administation

Sheet Revue Initialisation
E1: REVUE D'INITIALISATION PROJET
E2: Passation Commerce → Production — à compléter à la commande
A4: INFORMATIONS GÉNÉRALES DU PROJET
A5: Client | B5: =IF(Recap_FCI!C2="","",Recap_FCI!C2) -> Client | E5: Nom du projet (Affaire) | F5: =IF(Recap_FCI!C3="","",Recap_FCI!C3) -> Affaire | I5: Référence FCI / Axonaut | J5: À compléter
A6: Site | B6: =IF(Recap_FCI!C4="","",Recap_FCI!C4) | E6: Adresse chantier | F6: =IF(Recap_FCI!C5="","",Recap_FCI!C5) | I6: Type de bâtiment | J6: À compléter
A7: Technologie | B7: =IF(Recap_FCI!C6="","",Recap_FCI!C6) | E7: Offre | F7: =IF(Recap_FCI!C7="","",Recap_FCI!C7) | I7: N° Offre | J7: =IF(Recap_FCI!G2="","",Recap_FCI!G2)
A8: Phase projet | B8: À compléter | E8: Date de passation Commerce→Prod | I8: N° Commande client | J8: À compléter
A10: CONTACTS & INTERVENANTS
A11: Client Preneur | B11: =IF(Recap_FCI!L2="","",Recap_FCI!L2) -> Client Preneur : | E11: Maîtrise d'Ouvrage (MOA) | F11: =IF(Recap_FCI!L3="","",Recap_FCI!L3) -> Maitrise d'Ouvrage : | I11: Contact client (nom / tél / mail) | J11: À compléter
A12: Aménageur / BET / AMOA | B12: =IF(Recap_FCI!L4="","",Recap_FCI!L4) -> Aménageur / BET / AMOA : | E12: Maîtrise d'Œuvre (MOE) | F12: =IF(Recap_FCI!L5="","",Recap_FCI!L5) -> Maitrise d'Œuvre : | I12: Entrepreneur Principal | J12: =IF(Recap_FCI!L6="","",Recap_FCI!L6) -> Entrepreneur Principal :
A13: Architecte | B13: =IF(Recap_FCI!G3="","",Recap_FCI!G3) -> Woody SEALE | E13: BET | F13: =IF(Recap_FCI!G6="","",Recap_FCI!G6) | I13: Agence PROSYB | J13: =IF(Recap_FCI!G5="","",Recap_FCI!G5)
A15: ÉQUIPE PROJET PROSYB
A16: Responsable commercial / Ingénieur Affaires | B16: =IF(Recap_FCI!G4="","",Recap_FCI!G4) -> Woody SEALE | E16: Chargé d'affaire | F16: À compléter | I16: Conducteur de travaux pressenti | J16: À compléter
A17: Chef de chantier pressenti | B17: À compléter | E17: BET impliqué | F17: À compléter | I17: Heures internes prévues | J17: À compléter
A19: OBJECTIFS & ENJEUX
A20: Objectif principal du projet | C20: À compléter
A21: Contexte du projet | C21: À compléter
A22: Points forts du dossier | C22: À compléter
A23: Risques identifiés | C23: À compléter
A24: Alliés du projet | C24: À compléter
A25: Freins ou ennemis potentiels | C25: À compléter
A27: PLANNING PRÉVISIONNEL
A28: Date réception AO | B28: =IF(Recap_FCI!I2="","",Recap_FCI!I2) -> Date réception AO : | D28: Date revue offre | E28: =IF(Recap_FCI!I3="","",Recap_FCI!I3) -> Date Revue Offre : | G28: Date remise offre | H28: =IF(Recap_FCI!I4="","",Recap_FCI!I4) -> Date Remise Offre : | J28: Date soutenance | K28: =IF(Recap_FCI!I5="","",Recap_FCI!I5) -> Date Soutenance :
A29: Date décision | B29: =IF(Recap_FCI!I6="","",Recap_FCI!I6) -> Date Décision : | D29: Date début projet | E29: =IF(Recap_FCI!I7="","",Recap_FCI!I7) -> Date Début Projet : | G29: Début intervention prévue | J29: Fin estimée
A30: Délai global | B30: À compléter | D30: Date de MES promise | E30: =IF(Recap_FCI!G7="","",Recap_FCI!G7) | G30: Contraintes spécifiques | I30: À compléter
A32: CONDITIONS CONTRACTUELLES & FINANCIÈRES
A33: Conditions de règlement | B33: À compléter | E33: Retenue de garantie | F33: À compléter | I33: Pénalités de retard | J33: À compléter
A34: Modalités de facturation / échéancier | B34: À compléter | E34: Révision de prix | F34: À compléter | I34: Assurance décennale requise | J34: À compléter
A36: BUDGET & RESSOURCES
A37: Budget total vendu (HT) | B37: =IF(Recap_FCI!F13="","",Recap_FCI!F13) -> 0 | D37: Marge brute cible | E37: =IF(Recap_FCI!G15="","",Recap_FCI!G15) -> 0 | G37: Budget Matériel | H37: =IF(Recap_FCI!J13="","",Recap_FCI!J13) -> 0 | J37: Budget Main d'Œuvre | K37: =IF(Recap_FCI!I13="","",Recap_FCI!I13) -> 0
A38: Budget Sous-traitance (SSTT) | B38: =SUM(E42:E50) -> 0 | D38: Heures prévues internes | E38: À compléter | G38: Fournitures principales | I38: À compléter
A40: SOUS-TRAITANTS PRESSENTIS
A41: Sous-traitant | C41: Rôle | E41: Budget alloué | G41: Contact / Tél | I41: Devis reçu | K41: Contrat signé
I42: ☐ | K42: ☐
I43: ☐ | K43: ☐
I44: ☐ | K44: ☐
I45: ☐ | K45: ☐
I46: ☐ | K46: ☐
I47: ☐ | K47: ☐
I48: ☐ | K48: ☐
I49: ☐ | K49: ☐
I50: ☐ | K50: ☐
A52: CHECKLIST DOCUMENTS & PASSATION
A53: État | B53: Élément à vérifier / Document | K53: Commentaire
A54: ☐ | B54: Bon de commande obtenu et archivé (Axonaut + dossier partagé)
A55: ☐ | B55: Devis / DPGF chiffrage validé et signé
A56: ☐ | B56: Passation Commerce → Production réalisée et actée
A57: ☐ | B57: Acompte facturé / reçu (si applicable)
A58: ☐ | B58: CCTP / DCE transmis à la production
A59: ☐ | B59: Plans (existants / projet) transmis
A60: ☐ | B60: Planning prévisionnel communiqué au client
A61: ☐ | B61: Dossier client créé (Axonaut + dossier partagé)
A62: ☐ | B62: Sous-traitants consultés et devis reçus
A63: ☐ | B63: Contrats de sous-traitance signés
A64: ☐ | B64: Attestations d'assurance décennale sous-traitants vérifiées
A65: ☐ | B65: Déclaration de sous-traitance transmise au client (si nécessaire)
A66: ☐ | B66: Commande matériel initiée / fournisseurs consultés
A68: PARTICIPANTS À LA REVUE / VALIDATION
A69: Commerce | C69: Production | E69: Administratif | G69: Direction | I69: Client (si applicable) | K69: Autre
A70: Nom : | C70: Nom : | E70: Nom : | G70: Nom : | I70: Nom : | K70: Nom :
A71: Date : | C71: Date : | E71: Date : | G71: Date : | I71: Date : | K71: Date :
A72: Signature / Visa : | C72: Signature / Visa : | E72: Signature / Visa : | G72: Signature / Visa : | I72: Signature / Visa : | K72: Signature / Visa :
A74: À la fin de la revue, document à imprimer en PDF et à archiver dans le dossier projet (Axonaut + dossier partagé).
A75: PROSYB — Énergies et Connectivités | Revue d'Initialisation Projet — v2.0
